Workbook

Sheet Dashboard
A1: IDB BI Cost Comparator - Executive Dashboard (all 20 configurations)
A3: Planning case | B3: Value | C3: Cloud | D3: Configuration | E3: Licence model | F3: 5-year TCO | G3: Avg annual TCO | H3: Rank | I3: Rank in cloud | J3: Decision note | L3: Chart label
A4: Consumers | B4: =Inputs!$B$6 -> 500 | C4: AWS | D4: Power BI + Snowflake AWS | E4: Pro - all named | F4: ='TCO Comparison'!I5 -> 1438000 | G4: ='TCO Comparison'!J5 -> 287600 | H4: ='TCO Comparison'!L5 -> 11 | I4: ='TCO Comparison'!M5 -> 5 | J4: Cross-cloud; all named users | L4: =SUBSTITUTE(D4," + Snowflake ","/")&" - "&E4 -> Power BI/AWS - Pro - all named
A5: Developers + explorers | B5: =Inputs!$B$7+Inputs!$B$8 -> 50 | C5: AWS | D5: Power BI + Snowflake AWS | E5: PPU - all named | F5: ='TCO Comparison'!I6 -> 1768000 | G5: ='TCO Comparison'!J6 -> 353600 | H5: ='TCO Comparison'!L6 -> 18 | I5: ='TCO Comparison'!M6 -> 9 | J5: Feature-rich but costly at scale | L5: =SUBSTITUTE(D5," + Snowflake ","/")&" - "&E5 -> Power BI/AWS - PPU - all named
A6: BI traffic (TB/month) | B6: =Inputs!$B$10 -> 5 | C6: AWS | D6: Power BI + Snowflake AWS | E6: Fabric F64 Reserved + Pro | F6: ='TCO Comparison'!I7 -> 1318160.2 | G6: ='TCO Comparison'!J7 -> 263632.04 | H6: ='TCO Comparison'!L7 -> 8 | I6: ='TCO Comparison'!M7 -> 4 | J6: Recommended Power BI model; validate sizing | L6: =SUBSTITUTE(D6," + Snowflake ","/")&" - "&E6 -> Power BI/AWS - Fabric F64 Reserved + Pro
A7: Reports in scope | B7: =Inputs!$B$11 -> 250 | C7: AWS | D7: Power BI + Snowflake AWS | E7: Fabric F64 PAYG + Pro | F7: ='TCO Comparison'!I8 -> 1522576 | G7: ='TCO Comparison'!J8 -> 304515.2 | H7: ='TCO Comparison'!L8 -> 13 | I7: ='TCO Comparison'!M8 -> 7 | J7: PAYG benchmark | L7: =SUBSTITUTE(D7," + Snowflake ","/")&" - "&E7 -> Power BI/AWS - Fabric F64 PAYG + Pro
A8: TCO horizon (years) | B8: =Inputs!$B$12 -> 5 | C8: AWS | D8: Power BI + Snowflake AWS | E8: Premium P1 + Pro | F8: ='TCO Comparison'!I9 -> 1317700 | G8: ='TCO Comparison'!J9 -> 263540 | H8: ='TCO Comparison'!L9 -> 7 | I8: ='TCO Comparison'!M9 -> 3 | J8: Legacy reference only | L8: =SUBSTITUTE(D8," + Snowflake ","/")&" - "&E8 -> Power BI/AWS - Premium P1 + Pro
A9: Snowflake credit rate | B9: =Inputs!$B$36 -> 3 | C9: AWS | D9: Tableau Cloud + Snowflake AWS | E9: Standard role-based | F9: ='TCO Comparison'!I10 -> 1504500 | G9: ='TCO Comparison'!J10 -> 300900 | H9: ='TCO Comparison'!L10 -> 12 | I9: ='TCO Comparison'!M10 -> 6 | J9: Same-cloud SaaS (Hyperforce on AWS) | L9: =SUBSTITUTE(D9," + Snowflake ","/")&" - "&E9 -> Tableau Cloud/AWS - Standard role-based
C10: AWS | D10: Tableau Cloud + Snowflake AWS | E10: Tableau+ (AI tier) | F10: ='TCO Comparison'!I11 -> 2206500 | G10: ='TCO Comparison'!J11 -> 441300 | H10: ='TCO Comparison'!L11 -> 19 | I10: ='TCO Comparison'!M11 -> 10 | J10: Quote-only; floor estimate | L10: =SUBSTITUTE(D10," + Snowflake ","/")&" - "&E10 -> Tableau Cloud/AWS - Tableau+ (AI tier)
A11: Headline | B11: Value | C11: AWS | D11: Tableau Server + Snowflake AWS | E11: Standard role-based | F11: ='TCO Comparison'!I12 -> 1754500 | G11: ='TCO Comparison'!J12 -> 350900 | H11: ='TCO Comparison'!L12 -> 16 | I11: ='TCO Comparison'!M12 -> 8 | J11: Placement control; higher operations | L11: =SUBSTITUTE(D11," + Snowflake ","/")&" - "&E11 -> Tableau Server/AWS - Standard role-based
A12: Lowest 5-yr TCO - AWS (excl. P1) | B12: =MIN('TCO Comparison'!I5,'TCO Comparison'!I6,'TCO Comparison'!I7,'TCO Comparison'!I8,'TCO Comparison'!I10,'TCO Comparison'!I11,'TCO Comparison'!I12,'TCO Comparison'!I13,'TCO Comparison'!I14) -> 1137400 | C12: AWS | D12: QuickSight + Snowflake AWS | E12: Standard Author + Reader | F12: ='TCO Comparison'!I13 -> 1137400 | G12: ='TCO Comparison'!J13 -> 227480 | H12: ='TCO Comparison'!L13 -> 1 | I12: ='TCO Comparison'!M13 -> 1 | J12: AWS-aligned economic baseline | L12: =SUBSTITUTE(D12," + Snowflake ","/")&" - "&E12 -> QuickSight/AWS - Standard Author + Reader
A13: Lowest 5-yr TCO - Azure (excl. P1) | B13: =MIN('TCO Comparison'!I16,'TCO Comparison'!I17,'TCO Comparison'!I18,'TCO Comparison'!I19,'TCO Comparison'!I21,'TCO Comparison'!I22,'TCO Comparison'!I23,'TCO Comparison'!I24,'TCO Comparison'!I25) -> 1151160.2 | C13: AWS | D13: QuickSight + Snowflake AWS | E13: Author Pro + Q (AI) | F13: ='TCO Comparison'!I14 -> 1200400 | G13: ='TCO Comparison'!J14 -> 240080 | H13: ='TCO Comparison'!L14 -> 4 | I13: ='TCO Comparison'!M14 -> 2 | J13: Generative BI for authors | L13: =SUBSTITUTE(D13," + Snowflake ","/")&" - "&E13 -> QuickSight/AWS - Author Pro + Q (AI)
A14: Power BI cross-cloud premium / yr | B14: ='Cross-Cloud Premium'!G5 -> 33400 | C14: Azure | D14: Power BI + Snowflake Azure | E14: Pro - all named | F14: ='TCO Comparison'!I16 -> 1271000 | G14: ='TCO Comparison'!J16 -> 254200 | H14: ='TCO Comparison'!L16 -> 5 | I14: ='TCO Comparison'!M16 -> 3 | J14: Same-cloud Power BI baseline | L14: =SUBSTITUTE(D14," + Snowflake ","/")&" - "&E14 -> Power BI/Azure - Pro - all named
A15: Power BI cross-cloud premium / 5 yrs | B15: ='Cross-Cloud Premium'!C13 -> 167000 | C15: Azure | D15: Power BI + Snowflake Azure | E15: PPU - all named | F15: ='TCO Comparison'!I17 -> 1601000 | G15: ='TCO Comparison'!J17 -> 320200 | H15: ='TCO Comparison'!L17 -> 14 | I15: ='TCO Comparison'!M17 -> 7 | J15: Same-cloud PPU | L15: =SUBSTITUTE(D15," + Snowflake ","/")&" - "&E15 -> Power BI/Azure - PPU - all named
A16: Optimised PBI premium / yr | B16: ='Cross-Cloud Premium'!G25 -> 22240 | C16: Azure | D16: Power BI + Snowflake Azure | E16: Fabric F64 Reserved + Pro | F16: ='TCO Comparison'!I18 -> 1151160.2 | G16: ='TCO Comparison'!J18 -> 230232.04 | H16: ='TCO Comparison'!L18 -> 3 | I16: ='TCO Comparison'!M18 -> 2 | J16: Recommended Power BI model | L16: =SUBSTITUTE(D16," + Snowflake ","/")&" - "&E16 -> Power BI/Azure - Fabric F64 Reserved + Pro
C17: Azure | D17: Power BI + Snowflake Azure | E17: Fabric F64 PAYG + Pro | F17: ='TCO Comparison'!I19 -> 1355576 | G17: ='TCO Comparison'!J19 -> 271115.2 | H17: ='TCO Comparison'!L19 -> 9 | I17: ='TCO Comparison'!M19 -> 5 | J17: PAYG benchmark | L17: =SUBSTITUTE(D17," + Snowflake ","/")&" - "&E17 -> Power BI/Azure - Fabric F64 PAYG + Pro
C18: Azure | D18: Power BI + Snowflake Azure | E18: Premium P1 + Pro | F18: ='TCO Comparison'!I20 -> 1150700 | G18: ='TCO Comparison'!J20 -> 230140 | H18: ='TCO Comparison'!L20 -> 2 | I18: ='TCO Comparison'!M20 -> 1 | J18: Legacy reference only | L18: =SUBSTITUTE(D18," + Snowflake ","/")&" - "&E18 -> Power BI/Azure - Premium P1 + Pro
C19: Azure | D19: Tableau Cloud + Snowflake Azure | E19: Standard role-based | F19: ='TCO Comparison'!I21 -> 1609750 | G19: ='TCO Comparison'!J21 -> 321950 | H19: ='TCO Comparison'!L21 -> 15 | I19: ='TCO Comparison'!M21 -> 8 | J19: Cross-cloud SaaS (AWS to Azure) | L19: =SUBSTITUTE(D19," + Snowflake ","/")&" - "&E19 -> Tableau Cloud/Azure - Standard role-based
C20: Azure | D20: Tableau Cloud + Snowflake Azure | E20: Tableau+ (AI tier) | F20: ='TCO Comparison'!I22 -> 2311750 | G20: ='TCO Comparison'!J22 -> 462350 | H20: ='TCO Comparison'!L22 -> 20 | I20: ='TCO Comparison'!M22 -> 10 | J20: Quote-only; floor estimate | L20: =SUBSTITUTE(D20," + Snowflake ","/")&" - "&E20 -> Tableau Cloud/Azure - Tableau+ (AI tier)
C21: Azure | D21: Tableau Server + Snowflake Azure | E21: Standard role-based | F21: ='TCO Comparison'!I23 -> 1754500 | G21: ='TCO Comparison'!J23 -> 350900 | H21: ='TCO Comparison'!L23 -> 16 | I21: ='TCO Comparison'!M23 -> 9 | J21: Placement control; higher operations | L21: =SUBSTITUTE(D21," + Snowflake ","/")&" - "&E21 -> Tableau Server/Azure - Standard role-based
C22: Azure | D22: QuickSight + Snowflake Azure | E22: Standard Author + Reader | F22: ='TCO Comparison'!I24 -> 1297450 | G22: ='TCO Comparison'!J24 -> 259490 | H22: ='TCO Comparison'!L24 -> 6 | I22: ='TCO Comparison'!M24 -> 4 | J22: Cross-cloud QuickSight pattern | L22: =SUBSTITUTE(D22," + Snowflake ","/")&" - "&E22 -> QuickSight/Azure - Standard Author + Reader
C23: Azure | D23: QuickSight + Snowflake Azure | E23: Author Pro + Q (AI) | F23: ='TCO Comparison'!I25 -> 1360450 | G23: ='TCO Comparison'!J25 -> 272090 | H23: ='TCO Comparison'!L25 -> 10 | I23: ='TCO Comparison'!M25 -> 6 | J23: Cross-cloud with Pro authors | L23: =SUBSTITUTE(D23," + Snowflake ","/")&" - "&E23 -> QuickSight/Azure - Author Pro + Q (AI)
A25: Decision guide
A26: Snowflake target | B26: Provisional lead | D26: Balanced alternative | E26: Strategic interpretation
A27: AWS | B27: QuickSight | D27: Tableau | E27: Lowest TCO and native alignment; Power BI remains viable where semantic modelling, paginated reporting and M365 integration justify the cross-cloud premium.
A28: Azure | B28: Power BI | D28: Tableau | E28: Same-cloud alignment strengthens Power BI; Fabric F64 Reserved is the lowest Azure TCO - validate capacity sizing rather than assuming F64.
A29: Unresolved / multi-cloud | B29: Defer standard | D29: Tableau | E29: Keep Phase 2 cloud-neutral until target cloud and FIS-to-Snowflake readiness are confirmed.

Sheet Inputs
A1: IDB BI Cost Simulator v2 - Inputs and Assumptions
A2: Yellow cells with blue text are editable inputs. USD, excluding tax. Public list prices validated 23 Oct 2026; replace with IDB commercial quotes and measured PoV workloads before commitment.
A4: Workload assumptions (baseline = Large scenario)
A5: Input | B5: Value | C5: Unit | D5: Purpose | E5: Source / basis | F5: Notes
A6: Consumers | B6: 500 | C6: users | D6: Named report consumers | E6: IDB planning assumption | F6: Shared with POV
A7: Developers / creators | B7: 25 | C7: users | D7: Report and semantic-model developers | E7: IDB planning assumption | F7: Shared with POV
A8: Explorers / analysts | B8: 25 | C8: users | D8: Web authors / self-service analysts | E8: IDB planning assumption | F8: Licensed as author-class users on every platform
A9: Peak concurrency | B9: 100 | C9: users | D9: Capacity sizing input | E9: IDB planning assumption | F9: Validate in proof of value
A10: Monthly BI result traffic | B10: 5 | C10: TB/month | D10: Cross-cloud sensitivity | E10: IDB planning assumption | F10: Decimal TB: 1 TB = 1,000 GB
A11: Reports / dashboards | B11: 250 | C11: count | D11: Migration model | E11: IDB planning assumption | F11: Working migration scope; current estate is ~280
A12: Years in TCO | B12: 5 | C12: years | D12: TCO horizon | E12: Planning assumption
A13: Annual inflation | B13: 0 | C13: percent | D13: Recurring-cost escalation, years 2-N | E13: Planning assumption | F13: 0% baseline
A15: Commercial assumptions - per user / per account (public list, billed annually)
A16: Product / licence | B16: Price | C16: Unit | D16: Applied to | E16: Public source | F16: Validation status (23 Oct 2026)
A17: Power BI Pro | B17: 14 | C17: $/user/month | D17: All users (Pro/PPU models); creators + explorers (capacity models) | E17: https://www.microsoft.com/en-us/power-platform/products/power-bi/pricing | F17: Verified - official list, paid yearly
A18: Power BI Premium Per User | B18: 24 | C18: $/user/month | D18: All users of PPU content | E18: https://www.microsoft.com/en-us/power-platform/products/power-bi/pricing | F18: Verified - official list, paid yearly
A19: Tableau Creator (Standard) | B19: 75 | C19: $/user/month | D19: Developers / creators | E19: https://www.tableau.com/pricing/cloud | /pricing/server | F19: Verified - same list price for Cloud and Server
A20: Tableau Explorer (Standard) | B20: 42 | C20: $/user/month | D20: Explorers / analysts | E20: https://www.tableau.com/pricing/cloud | /pricing/server | F20: Verified
A21: Tableau Viewer (Standard) | B21: 15 | C21: $/user/month | D21: Consumers | E21: https://www.tableau.com/pricing/cloud | /pricing/server | F21: Verified
A22: Tableau+ Creator (planning) | B22: 115 | C22: $/user/month | D22: Tableau+ AI tier - creators | E22: https://www.tableau.com/pricing/cloud | /pricing/server | F22: Tableau+ is quote-only; Enterprise list ($115) used as price floor
A23: Tableau+ Explorer (planning) | B23: 70 | C23: $/user/month | D23: Tableau+ AI tier - explorers | E23: https://www.tableau.com/pricing/cloud | /pricing/server | F23: Quote-only; Enterprise list ($70) used as floor
A24: Tableau+ Viewer (planning) | B24: 35 | C24: $/user/month | D24: Tableau+ AI tier - viewers | E24: https://www.tableau.com/pricing/cloud | /pricing/server | F24: Quote-only; Enterprise list ($35) used as floor
A25: QuickSight Author | B25: 24 | C25: $/user/month | D25: Developers and explorers (Standard) | E25: https://aws.amazon.com/quick/quicksight/pricing/ | F25: Verified - now 'Amazon Quick Sight' in Quick Suite
A26: QuickSight Author Pro | B26: 40 | C26: $/user/month | D26: Developers and explorers (AI tier) | E26: https://aws.amazon.com/quick/quicksight/pricing/ | F26: Verified - includes generative BI
A27: QuickSight Reader | B27: 3 | C27: $/user/month | D27: Consumers | E27: https://aws.amazon.com/quick/quicksight/pricing/ | F27: Verified
A28: QuickSight Reader Pro | B28: 20 | C28: $/user/month | D28: Consumers - full Pro reference only | E28: https://aws.amazon.com/quick/quicksight/pricing/ | F28: Verified
A29: QuickSight account infrastructure fee | B29: 250 | C29: $/account/month | D29: Any Pro user or Q&A topics enabled | E29: https://aws.amazon.com/quick/quicksight/pricing/ | F29: Verified
A31: Capacity and platform rates
A32: Cost item | B32: Value | C32: Unit | D32: Applied to | E32: Public source | F32: Validation status (23 Oct 2026)
A33: Fabric F64 pay-as-you-go | B33: 8409.6 | C33: $/month | D33: Power BI capacity (PAYG) | E33: https://azure.microsoft.com/en-us/pricing/details/microsoft-fabric/ | F33: Verified - US list ($0.18/CU-hr x 64 CU x 730 h)
A34: Fabric F64 1-year reservation | B34: 5002.67 | C34: $/month | D34: Power BI capacity (reserved) | E34: https://azure.microsoft.com/en-us/pricing/details/microsoft-fabric/ | F34: Verified - ~40.5% saving vs PAYG
A35: Power BI Premium P1 (legacy) | B35: 4995 | C35: $/month | D35: Power BI capacity (legacy) | E35: https://learn.microsoft.com/en-us/power-bi/support/premium-migration-overview | F35: No new P SKU sales; renewal only under an active EA
A36: Snowflake credit rate | B36: 3 | C36: $/credit | D36: Base BI Snowflake compute | E36: https://www.snowflake.com/pricing/pricing-guide | F36: Verified - Enterprise, AWS US East on-demand; Business Critical = $4
A38: Delivery and operating assumptions
A39: Cost item | B39: Value | C39: Unit | D39: Applied to | E39: Basis | F39: Notes
A40: Tableau Server infrastructure | B40: 30000 | C40: $/year | D40: Tableau Server | E40: Planning assumption | F40: Compute, HA, backup, monitoring
A41: AWS gateway cluster (Power BI) | B41: 6000 | C41: $/year | D41: Power BI with Snowflake on AWS | E41: Planning assumption | F41: Two-node gateway on EC2; set to zero if not required
A42: Base platform operations - Power BI | B42: 20000 | C42: $/year | D42: Power BI | E42: Planning assumption | F42: Admin, monitoring, release support
A43: Base platform operations - Tableau Cloud | B43: 25000 | C43: $/year | D43: Tableau Cloud | E43: Planning assumption | F43: Admin, governance and support
A44: Base platform operations - Tableau Server | B44: 45000 | C44: $/year | D44: Tableau Server | E44: Planning assumption | F44: Infrastructure and BI administration
A45: Base platform operations - QuickSight | B45: 15000 | C45: $/year | D45: QuickSight | E45: Planning assumption | F45: Admin, governance and support
A46: Migration cost per report - Power BI | B46: 2500 | C46: $/report | D46: Power BI | E46: Planning assumption | F46: Average blended effort
A47: Migration cost per report - Tableau | B47: 2700 | C47: $/report | D47: Tableau | E47: Planning assumption | F47: Average blended effort
A48: Migration cost per report - QuickSight | B48: 3200 | C48: $/report | D48: QuickSight | E48: Planning assumption | F48: Average blended effort
A49: Training / enablement - Power BI | B49: 30000 | C49: $ one-time | D49: Power BI | E49: Planning assumption | F49: Year 1
A50: Training / enablement - Tableau | B50: 25000 | C50: $ one-time | D50: Tableau | E50: Planning assumption | F50: Year 1
A51: Training / enablement - QuickSight | B51: 50000 | C51: $ one-time | D51: QuickSight | E51: Planning assumption | F51: Year 1
A53: Architecture and cross-cloud assumptions
A54: Input | B54: Value | C54: Unit | D54: Purpose | E54: Basis | F54: Notes
A55: Cross-cloud transfer rate | B55: 0.09 | C55: $/GB | D55: Conservative data-movement sensitivity | E55: https://www.snowflake.com/pricing/pricing-guide ($90/TB to other cloud) | F55: Snowflake does not bill egress for driver-retrieved query results; applies to gateway/NAT egress from AWS
A56: Private-path transfer rate | B56: 0.02 | C56: $/GB | D56: Direct Connect / interconnect lever | E56: Planning assumption | F56: Excludes fixed circuit, port and provider charges
A57: Import / incremental-refresh transfer reduction | B57: 0.8 | C57: percent | D57: Optimisation lever | E57: Planning assumption | F57: Validate with change rate and partitions
A58: Incremental compute reduction (aggregations, caching) | B58: 0.5 | C58: percent | D58: Optimisation lever | E58: Planning assumption | F58: Result cache, aggregations, warehouse auto-suspend
A59: Power BI incremental Snowflake compute (cross-cloud) | B59: 12000 | C59: $/year | D59: AWS cross-cloud workload premium | E59: Expected-case assumption | F59: Scaled by consumers in Scenario Simulator
A60: Tableau Cloud cross-cloud factor - Snowflake on Azure | B60: 0.75 | C60: factor | D60: Relative to Power BI premium | E60: Planning assumption | F60: Tableau Cloud runs on AWS (Salesforce Hyperforce)
A61: Tableau Cloud cross-cloud factor - Snowflake on AWS | B61: 0 | C61: factor | D61: Relative to Power BI premium | E61: Tableau Cloud on Hyperforce on AWS | F61: 0 = site in same AWS region as Snowflake; set 0.75 if not aligned
A62: QuickSight cross-cloud factor - Snowflake on Azure | B62: 1.15 | C62: factor | D62: Azure-to-AWS relative premium | E62: Planning assumption
A63: Power BI additional cross-cloud operations | B63: 10000 | C63: $/year | D63: Network, security and support | E63: Expected-case assumption
A64: Tableau Cloud additional cross-cloud operations | B64: 8000 | C64: $/year | D64: Pod, network and support | E64: Planning assumption | F64: Applied only when the cross-cloud factor > 0
A65: QuickSight additional cross-cloud operations | B65: 12000 | C65: $/year | D65: Azure-to-AWS integration and support | E65: Planning assumption
A66: Snowflake credits/month - Power BI | B66: 300 | C66: credits/month | D66: Base BI workload | E66: Planning assumption
A67: Snowflake credits/month - Tableau | B67: 300 | C67: credits/month | D67: Base BI workload | E67: Planning assumption
A68: Snowflake credits/month - QuickSight | B68: 280 | C68: credits/month | D68: Base BI workload | E68: Planning assumption | F68: SPICE caching reduces live queries

Sheet License Calculator
A1: Annual BI Licensing Calculator - baseline named users
A2: All formulas reference Inputs. Explorers/analysts are licensed as author-class users on every platform for a like-for-like comparison.
A3: Licensing model | B3: Developer / creator cost | C3: Explorer / analyst cost | D3: Consumer cost | E3: Capacity / account cost | F3: Annual licence total | G3: Who needs paid licences | H3: Notes
A4: Power BI Pro - all named users | B4: =Inputs!$B$7*Inputs!$B$17*12 -> 4200 | C4: =Inputs!$B$8*Inputs!$B$17*12 -> 4200 | D4: =Inputs!$B$6*Inputs!$B$17*12 -> 84000 | E4: =0 -> 0 | F4: =SUM(B4:E4) -> 92400 | G4: Creators, explorers and consumers | H4: Shared capacity; no Copilot
A5: Power BI PPU - all named users | B5: =Inputs!$B$7*Inputs!$B$18*12 -> 7200 | C5: =Inputs!$B$8*Inputs!$B$18*12 -> 7200 | D5: =Inputs!$B$6*Inputs!$B$18*12 -> 144000 | E5: =0 -> 0 | F5: =SUM(B5:E5) -> 158400 | G5: Every PPU content user | H5: Premium features per user
A6: Fabric F64 Reserved + Pro authors | B6: =Inputs!$B$7*Inputs!$B$17*12 -> 4200 | C6: =Inputs!$B$8*Inputs!$B$17*12 -> 4200 | D6: =0 -> 0 | E6: =Inputs!$B$34*12 -> 60032.04 | F6: =SUM(B6:E6) -> 68432.04 | G6: Creators and explorers on Pro; viewers free at F64+ | H6: Recommended Power BI model at 500 consumers; Copilot uses capacity
A7: Fabric F64 PAYG + Pro authors | B7: =Inputs!$B$7*Inputs!$B$17*12 -> 4200 | C7: =Inputs!$B$8*Inputs!$B$17*12 -> 4200 | D7: =0 -> 0 | E7: =Inputs!$B$33*12 -> 100915.2 | F7: =SUM(B7:E7) -> 109315.2 | G7: Creators and explorers on Pro; viewers free at F64+ | H7: Flexible, ~68% dearer than reserved
A8: Premium P1 + Pro authors (legacy) | B8: =Inputs!$B$7*Inputs!$B$17*12 -> 4200 | C8: =Inputs!$B$8*Inputs!$B$17*12 -> 4200 | D8: =0 -> 0 | E8: =Inputs!$B$35*12 -> 59940 | F8: =SUM(B8:E8) -> 68340 | G8: Creators and explorers on Pro; viewers free at P1 | H8: Legacy reference - no new P SKU purchases
A9: Tableau Standard role-based (Cloud or Server) | B9: =Inputs!$B$7*Inputs!$B$19*12 -> 22500 | C9: =Inputs!$B$8*Inputs!$B$20*12 -> 12600 | D9: =Inputs!$B$6*Inputs!$B$21*12 -> 90000 | E9: =0 -> 0 | F9: =SUM(B9:E9) -> 125100 | G9: Creator, Explorer and Viewer | H9: Same list price for Cloud and Server
A10: Tableau+ AI tier (planning floor) | B10: =Inputs!$B$7*Inputs!$B$22*12 -> 34500 | C10: =Inputs!$B$8*Inputs!$B$23*12 -> 21000 | D10: =Inputs!$B$6*Inputs!$B$24*12 -> 210000 | E10: =0 -> 0 | F10: =SUM(B10:E10) -> 265500 | G10: All roles upgraded | H10: Quote-only; Enterprise list used as floor
A11: QuickSight Standard - Author + Reader | B11: =Inputs!$B$7*Inputs!$B$25*12 -> 7200 | C11: =Inputs!$B$8*Inputs!$B$25*12 -> 7200 | D11: =Inputs!$B$6*Inputs!$B$27*12 -> 18000 | E11: =0 -> 0 | F11: =SUM(B11:E11) -> 32400 | G11: Developers and explorers as Authors; Readers | H11: Explorers licensed as Authors (like-for-like)
A12: QuickSight Author Pro + Reader (AI) | B12: =Inputs!$B$7*Inputs!$B$26*12 -> 12000 | C12: =Inputs!$B$8*Inputs!$B$26*12 -> 12000 | D12: =Inputs!$B$6*Inputs!$B$27*12 -> 18000 | E12: =Inputs!$B$29*12 -> 3000 | F12: =SUM(B12:E12) -> 45000 | G12: Pro authors and explorers; standard Readers | H12: Generative BI for authors + $250/month account fee
A13: QuickSight full Pro - Author Pro + Reader Pro | B13: =Inputs!$B$7*Inputs!$B$26*12 -> 12000 | C13: =Inputs!$B$8*Inputs!$B$26*12 -> 12000 | D13: =Inputs!$B$6*Inputs!$B$28*12 -> 120000 | E13: =Inputs!$B$29*12 -> 3000 | F13: =SUM(B13:E13) -> 147000 | G13: All users Pro | H13: Reference only - not in TCO
A15: Break-even checks
A16: Check | B16: Value | C16: Unit | G16: Interpretation
A17: F64 Reserved vs Pro: consumer break-even | B17: =Inputs!$B$34*12/(Inputs!$B$17*12) -> 357.33357 | C17: consumers | G17: Above this many consumers, F64 Reserved + Pro authors is cheaper than Pro for all
A18: F64 PAYG vs Pro: consumer break-even | B18: =Inputs!$B$33*12/(Inputs!$B$17*12) -> 600.68571 | C18: consumers | G18: PAYG capacity needs a much larger audience
A19: PPU vs F64 Reserved + Pro: total-user break-even | B19: =(Inputs!$B$34*12+(Inputs!$B$7+Inputs!$B$8)*Inputs!$B$17*12)/(Inputs!$B$18*12) -> 237.61125 | C19: named users | G19: Above this total, PPU for everyone costs more than F64 Reserved + Pro authors
A20: Tableau+ uplift vs Standard (baseline) | B20: =F10-F9 -> 140400 | C20: $/year | G20: AI tier premium at floor pricing
A21: QuickSight Author Pro uplift vs Standard (baseline) | B21: =F12-F11 -> 12600 | C21: $/year | G21: Includes $250/month account fee

Sheet Architecture Costs
A1: Annual Architecture and Operating Cost Derivation - baseline
A2: Transfer = TB/month x 1,000 x 12 x $/GB x factor. Base Snowflake compute = credits/month x 12 x credit rate.
A3: Configuration | B3: Cloud alignment | C3: Annual data transfer | D3: Incremental Snowflake compute | E3: Gateway / server infra | F3: Platform operations | G3: Base Snowflake compute | H3: Annual architecture & ops | I3: Formula logic | J3: Comments
A4: Power BI + Snowflake AWS | B4: Cross-cloud | C4: =Inputs!$B$10*1000*12*Inputs!$B$55 -> 5400 | D4: =Inputs!$B$59*1 -> 12000 | E4: =Inputs!$B$41 -> 6000 | F4: =Inputs!$B$42+Inputs!$B$63 -> 30000 | G4: =Inputs!$B$66*12*Inputs!$B$36 -> 10800 | H4: =SUM(C4:G4) -> 64200 | I4: Power BI service (Azure) reads AWS-hosted Snowflake via EC2 gateway | J4: Validate actual billing path
A5: Power BI + Snowflake Azure | B5: Same cloud | C5: =0 -> 0 | D5: =0 -> 0 | E5: =0 -> 0 | F5: =Inputs!$B$42 -> 20000 | G5: =Inputs!$B$66*12*Inputs!$B$36 -> 10800 | H5: =SUM(C5:G5) -> 30800 | I5: Base operations + base Snowflake | J5: Align regions
A6: Tableau Cloud + Snowflake AWS | B6: Same cloud (AWS) | C6: =Inputs!$B$10*1000*12*Inputs!$B$55*Inputs!$B$61 -> 0 | D6: =Inputs!$B$59*Inputs!$B$61*1 -> 0 | E6: =0 -> 0 | F6: =Inputs!$B$43+IF(Inputs!$B$61>0,Inputs!$B$64,0) -> 25000 | G6: =Inputs!$B$67*12*Inputs!$B$36 -> 10800 | H6: =SUM(C6:G6) -> 35800 | I6: Tableau Cloud runs on Hyperforce on AWS | J6: Confirm site region = Snowflake region
A7: Tableau Cloud + Snowflake Azure | B7: Cross-cloud | C7: =Inputs!$B$10*1000*12*Inputs!$B$55*Inputs!$B$60 -> 4050 | D7: =Inputs!$B$59*Inputs!$B$60*1 -> 9000 | E7: =0 -> 0 | F7: =Inputs!$B$43+IF(Inputs!$B$60>0,Inputs!$B$64,0) -> 33000 | G7: =Inputs!$B$67*12*Inputs!$B$36 -> 10800 | H7: =SUM(C7:G7) -> 56850 | I7: Scaled transfer and compute + operations | J7: AWS-hosted SaaS to Azure Snowflake
A8: Tableau Server + Snowflake AWS | B8: Same cloud | C8: =0 -> 0 | D8: =0 -> 0 | E8: =Inputs!$B$40 -> 30000 | F8: =Inputs!$B$44 -> 45000 | G8: =Inputs!$B$67*12*Inputs!$B$36 -> 10800 | H8: =SUM(C8:G8) -> 85800 | I8: Server infra + operations + base Snowflake | J8: Server placed on AWS
A9: Tableau Server + Snowflake Azure | B9: Same cloud | C9: =0 -> 0 | D9: =0 -> 0 | E9: =Inputs!$B$40 -> 30000 | F9: =Inputs!$B$44 -> 45000 | G9: =Inputs!$B$67*12*Inputs!$B$36 -> 10800 | H9: =SUM(C9:G9) -> 85800 | I9: Server infra + operations + base Snowflake | J9: Server placed on Azure
A10: QuickSight + Snowflake AWS | B10: Same cloud | C10: =0 -> 0 | D10: =0 -> 0 | E10: =0 -> 0 | F10: =Inputs!$B$45 -> 15000 | G10: =Inputs!$B$68*12*Inputs!$B$36 -> 10080 | H10: =SUM(C10:G10) -> 25080 | I10: Operations + base Snowflake | J10: AWS-native
A11: QuickSight + Snowflake Azure | B11: Cross-cloud | C11: =Inputs!$B$10*1000*12*Inputs!$B$55*Inputs!$B$62 -> 6210 | D11: =Inputs!$B$59*Inputs!$B$62*1 -> 13800 | E11: =0 -> 0 | F11: =Inputs!$B$45+Inputs!$B$65 -> 27000 | G11: =Inputs!$B$68*12*Inputs!$B$36 -> 10080 | H11: =SUM(C11:G11) -> 57090 | I11: Scaled transfer and compute + operations | J11: Azure-to-AWS pattern

Sheet TCO Comparison
A1: Five-Year Total Cost of Ownership - all 20 configurations (baseline 500 consumers / 25 developers / 25 explorers / 5 TB)
A2: Year 1 = recurring + one-time migration + training. Years 2-N = recurring with inflation. Rank 1 = lowest N-year TCO across all 20.
A3: Configuration | B3: Licence model | C3: Annual licensing | D3: Annual arch & ops | E3: One-time migration | F3: One-time training | G3: Year 1 TCO | H3: Years 2-N recurring | I3: N-year TCO | J3: Average annual TCO | K3: Cost per consumer / year | L3: Rank | M3: Rank in cloud | N3: Decision note
A4: Snowflake on AWS
A5: Power BI + Snowflake AWS | B5: Pro - all named | C5: ='License Calculator'!F4 -> 92400 | D5: ='Architecture Costs'!H4 -> 64200 | E5: =Inputs!$B$11*Inputs!$B$46 -> 625000 | F5: =Inputs!$B$49 -> 30000 | G5: =SUM(C5:F5) -> 811600 | H5: =IF(Inputs!$B$13=0,(C5+D5)*(Inputs!$B$12-1),(C5+D5)*(((1+Inputs!$B$13)^Inputs!$B$12-(1+Inputs!$B$13))/Inputs!$B$13)) -> 626400 | I5: =G5+H5 -> 1438000 | J5: =I5/Inputs!$B$12 -> 287600 | K5: =I5/Inputs!$B$12/Inputs!$B$6 -> 575.2 | L5: =RANK(I5,$I$5:$I$25,1) -> 11 | M5: =RANK(I5,$I$5:$I$14,1) -> 5 | N5: Cross-cloud; all named users
A6: Power BI + Snowflake AWS | B6: PPU - all named | C6: ='License Calculator'!F5 -> 158400 | D6: ='Architecture Costs'!H4 -> 64200 | E6: =Inputs!$B$11*Inputs!$B$46 -> 625000 | F6: =Inputs!$B$49 -> 30000 | G6: =SUM(C6:F6) -> 877600 | H6: =IF(Inputs!$B$13=0,(C6+D6)*(Inputs!$B$12-1),(C6+D6)*(((1+Inputs!$B$13)^Inputs!$B$12-(1+Inputs!$B$13))/Inputs!$B$13)) -> 890400 | I6: =G6+H6 -> 1768000 | J6: =I6/Inputs!$B$12 -> 353600 | K6: =I6/Inputs!$B$12/Inputs!$B$6 -> 707.2 | L6: =RANK(I6,$I$5:$I$25,1) -> 18 | M6: =RANK(I6,$I$5:$I$14,1) -> 9 | N6: Feature-rich but costly at scale
A7: Power BI + Snowflake AWS | B7: Fabric F64 Reserved + Pro | C7: ='License Calculator'!F6 -> 68432.04 | D7: ='Architecture Costs'!H4 -> 64200 | E7: =Inputs!$B$11*Inputs!$B$46 -> 625000 | F7: =Inputs!$B$49 -> 30000 | G7: =SUM(C7:F7) -> 787632.04 | H7: =IF(Inputs!$B$13=0,(C7+D7)*(Inputs!$B$12-1),(C7+D7)*(((1+Inputs!$B$13)^Inputs!$B$12-(1+Inputs!$B$13))/Inputs!$B$13)) -> 530528.16 | I7: =G7+H7 -> 1318160.2 | J7: =I7/Inputs!$B$12 -> 263632.04 | K7: =I7/Inputs!$B$12/Inputs!$B$6 -> 527.26408 | L7: =RANK(I7,$I$5:$I$25,1) -> 8 | M7: =RANK(I7,$I$5:$I$14,1) -> 4 | N7: Recommended Power BI model; validate sizing
A8: Power BI + Snowflake AWS | B8: Fabric F64 PAYG + Pro | C8: ='License Calculator'!F7 -> 109315.2 | D8: ='Architecture Costs'!H4 -> 64200 | E8: =Inputs!$B$11*Inputs!$B$46 -> 625000 | F8: =Inputs!$B$49 -> 30000 | G8: =SUM(C8:F8) -> 828515.2 | H8: =IF(Inputs!$B$13=0,(C8+D8)*(Inputs!$B$12-1),(C8+D8)*(((1+Inputs!$B$13)^Inputs!$B$12-(1+Inputs!$B$13))/Inputs!$B$13)) -> 694060.8 | I8: =G8+H8 -> 1522576 | J8: =I8/Inputs!$B$12 -> 304515.2 | K8: =I8/Inputs!$B$12/Inputs!$B$6 -> 609.0304 | L8: =RANK(I8,$I$5:$I$25,1) -> 13 | M8: =RANK(I8,$I$5:$I$14,1) -> 7 | N8: PAYG benchmark
A9: Power BI + Snowflake AWS | B9: Premium P1 + Pro | C9: ='License Calculator'!F8 -> 68340 | D9: ='Architecture Costs'!H4 -> 64200 | E9: =Inputs!$B$11*Inputs!$B$46 -> 625000 | F9: =Inputs!$B$49 -> 30000 | G9: =SUM(C9:F9) -> 787540 | H9: =IF(Inputs!$B$13=0,(C9+D9)*(Inputs!$B$12-1),(C9+D9)*(((1+Inputs!$B$13)^Inputs!$B$12-(1+Inputs!$B$13))/Inputs!$B$13)) -> 530160 | I9: =G9+H9 -> 1317700 | J9: =I9/Inputs!$B$12 -> 263540 | K9: =I9/Inputs!$B$12/Inputs!$B$6 -> 527.08 | L9: =RANK(I9,$I$5:$I$25,1) -> 7 | M9: =RANK(I9,$I$5:$I$14,1) -> 3 | N9: Legacy reference only
A10: Tableau Cloud + Snowflake AWS | B10: Standard role-based | C10: ='License Calculator'!F9 -> 125100 | D10: ='Architecture Costs'!H6 -> 35800 | E10: =Inputs!$B$11*Inputs!$B$47 -> 675000 | F10: =Inputs!$B$50 -> 25000 | G10: =SUM(C10:F10) -> 860900 | H10: =IF(Inputs!$B$13=0,(C10+D10)*(Inputs!$B$12-1),(C10+D10)*(((1+Inputs!$B$13)^Inputs!$B$12-(1+Inputs!$B$13))/Inputs!$B$13)) -> 643600 | I10: =G10+H10 -> 1504500 | J10: =I10/Inputs!$B$12 -> 300900 | K10: =I10/Inputs!$B$12/Inputs!$B$6 -> 601.8 | L10: =RANK(I10,$I$5:$I$25,1) -> 12 | M10: =RANK(I10,$I$5:$I$14,1) -> 6 | N10: Same-cloud SaaS (Hyperforce on AWS)
A11: Tableau Cloud + Snowflake AWS | B11: Tableau+ (AI tier) | C11: ='License Calculator'!F10 -> 265500 | D11: ='Architecture Costs'!H6 -> 35800 | E11: =Inputs!$B$11*Inputs!$B$47 -> 675000 | F11: =Inputs!$B$50 -> 25000 | G11: =SUM(C11:F11) -> 1001300 | H11: =IF(Inputs!$B$13=0,(C11+D11)*(Inputs!$B$12-1),(C11+D11)*(((1+Inputs!$B$13)^Inputs!$B$12-(1+Inputs!$B$13))/Inputs!$B$13)) -> 1205200 | I11: =G11+H11 -> 2206500 | J11: =I11/Inputs!$B$12 -> 441300 | K11: =I11/Inputs!$B$12/Inputs!$B$6 -> 882.6 | L11: =RANK(I11,$I$5:$I$25,1) -> 19 | M11: =RANK(I11,$I$5:$I$14,1) -> 10 | N11: Quote-only; floor estimate
A12: Tableau Server + Snowflake AWS | B12: Standard role-based | C12: ='License Calculator'!F9 -> 125100 | D12: ='Architecture Costs'!H8 -> 85800 | E12: =Inputs!$B$11*Inputs!$B$47 -> 675000 | F12: =Inputs!$B$50 -> 25000 | G12: =SUM(C12:F12) -> 910900 | H12: =IF(Inputs!$B$13=0,(C12+D12)*(Inputs!$B$12-1),(C12+D12)*(((1+Inputs!$B$13)^Inputs!$B$12-(1+Inputs!$B$13))/Inputs!$B$13)) -> 843600 | I12: =G12+H12 -> 1754500 | J12: =I12/Inputs!$B$12 -> 350900 | K12: =I12/Inputs!$B$12/Inputs!$B$6 -> 701.8 | L12: =RANK(I12,$I$5:$I$25,1) -> 16 | M12: =RANK(I12,$I$5:$I$14,1) -> 8 | N12: Placement control; higher operations
A13: QuickSight + Snowflake AWS | B13: Standard Author + Reader | C13: ='License Calculator'!F11 -> 32400 | D13: ='Architecture Costs'!H10 -> 25080 | E13: =Inputs!$B$11*Inputs!$B$48 -> 800000 | F13: =Inputs!$B$51 -> 50000 | G13: =SUM(C13:F13) -> 907480 | H13: =IF(Inputs!$B$13=0,(C13+D13)*(Inputs!$B$12-1),(C13+D13)*(((1+Inputs!$B$13)^Inputs!$B$12-(1+Inputs!$B$13))/Inputs!$B$13)) -> 229920 | I13: =G13+H13 -> 1137400 | J13: =I13/Inputs!$B$12 -> 227480 | K13: =I13/Inputs!$B$12/Inputs!$B$6 -> 454.96 | L13: =RANK(I13,$I$5:$I$25,1) -> 1 | M13: =RANK(I13,$I$5:$I$14,1) -> 1 | N13: AWS-aligned economic baseline
A14: QuickSight + Snowflake AWS | B14: Author Pro + Q (AI) | C14: ='License Calculator'!F12 -> 45000 | D14: ='Architecture Costs'!H10 -> 25080 | E14: =Inputs!$B$11*Inputs!$B$48 -> 800000 | F14: =Inputs!$B$51 -> 50000 | G14: =SUM(C14:F14) -> 920080 | H14: =IF(Inputs!$B$13=0,(C14+D14)*(Inputs!$B$12-1),(C14+D14)*(((1+Inputs!$B$13)^Inputs!$B$12-(1+Inputs!$B$13))/Inputs!$B$13)) -> 280320 | I14: =G14+H14 -> 1200400 | J14: =I14/Inputs!$B$12 -> 240080 | K14: =I14/Inputs!$B$12/Inputs!$B$6 -> 480.16 | L14: =RANK(I14,$I$5:$I$25,1) -> 4 | M14: =RANK(I14,$I$5:$I$14,1) -> 2 | N14: Generative BI for authors
A15: Snowflake on Azure
A16: Power BI + Snowflake Azure | B16: Pro - all named | C16: ='License Calculator'!F4 -> 92400 | D16: ='Architecture Costs'!H5 -> 30800 | E16: =Inputs!$B$11*Inputs!$B$46 -> 625000 | F16: =Inputs!$B$49 -> 30000 | G16: =SUM(C16:F16) -> 778200 | H16: =IF(Inputs!$B$13=0,(C16+D16)*(Inputs!$B$12-1),(C16+D16)*(((1+Inputs!$B$13)^Inputs!$B$12-(1+Inputs!$B$13))/Inputs!$B$13)) -> 492800 | I16: =G16+H16 -> 1271000 | J16: =I16/Inputs!$B$12 -> 254200 | K16: =I16/Inputs!$B$12/Inputs!$B$6 -> 508.4 | L16: =RANK(I16,$I$5:$I$25,1) -> 5 | M16: =RANK(I16,$I$16:$I$25,1) -> 3 | N16: Same-cloud Power BI baseline
A17: Power BI + Snowflake Azure | B17: PPU - all named | C17: ='License Calculator'!F5 -> 158400 | D17: ='Architecture Costs'!H5 -> 30800 | E17: =Inputs!$B$11*Inputs!$B$46 -> 625000 | F17: =Inputs!$B$49 -> 30000 | G17: =SUM(C17:F17) -> 844200 | H17: =IF(Inputs!$B$13=0,(C17+D17)*(Inputs!$B$12-1),(C17+D17)*(((1+Inputs!$B$13)^Inputs!$B$12-(1+Inputs!$B$13))/Inputs!$B$13)) -> 756800 | I17: =G17+H17 -> 1601000 | J17: =I17/Inputs!$B$12 -> 320200 | K17: =I17/Inputs!$B$12/Inputs!$B$6 -> 640.4 | L17: =RANK(I17,$I$5:$I$25,1) -> 14 | M17: =RANK(I17,$I$16:$I$25,1) -> 7 | N17: Same-cloud PPU
A18: Power BI + Snowflake Azure | B18: Fabric F64 Reserved + Pro | C18: ='License Calculator'!F6 -> 68432.04 | D18: ='Architecture Costs'!H5 -> 30800 | E18: =Inputs!$B$11*Inputs!$B$46 -> 625000 | F18: =Inputs!$B$49 -> 30000 | G18: =SUM(C18:F18) -> 754232.04 | H18: =IF(Inputs!$B$13=0,(C18+D18)*(Inputs!$B$12-1),(C18+D18)*(((1+Inputs!$B$13)^Inputs!$B$12-(1+Inputs!$B$13))/Inputs!$B$13)) -> 396928.16 | I18: =G18+H18 -> 1151160.2 | J18: =I18/Inputs!$B$12 -> 230232.04 | K18: =I18/Inputs!$B$12/Inputs!$B$6 -> 460.46408 | L18: =RANK(I18,$I$5:$I$25,1) -> 3 | M18: =RANK(I18,$I$16:$I$25,1) -> 2 | N18: Recommended Power BI model
A19: Power BI + Snowflake Azure | B19: Fabric F64 PAYG + Pro | C19: ='License Calculator'!F7 -> 109315.2 | D19: ='Architecture Costs'!H5 -> 30800 | E19: =Inputs!$B$11*Inputs!$B$46 -> 625000 | F19: =Inputs!$B$49 -> 30000 | G19: =SUM(C19:F19) -> 795115.2 | H19: =IF(Inputs!$B$13=0,(C19+D19)*(Inputs!$B$12-1),(C19+D19)*(((1+Inputs!$B$13)^Inputs!$B$12-(1+Inputs!$B$13))/Inputs!$B$13)) -> 560460.8 | I19: =G19+H19 -> 1355576 | J19: =I19/Inputs!$B$12 -> 271115.2 | K19: =I19/Inputs!$B$12/Inputs!$B$6 -> 542.2304 | L19: =RANK(I19,$I$5:$I$25,1) -> 9 | M19: =RANK(I19,$I$16:$I$25,1) -> 5 | N19: PAYG benchmark
A20: Power BI + Snowflake Azure | B20: Premium P1 + Pro | C20: ='License Calculator'!F8 -> 68340 | D20: ='Architecture Costs'!H5 -> 30800 | E20: =Inputs!$B$11*Inputs!$B$46 -> 625000 | F20: =Inputs!$B$49 -> 30000 | G20: =SUM(C20:F20) -> 754140 | H20: =IF(Inputs!$B$13=0,(C20+D20)*(Inputs!$B$12-1),(C20+D20)*(((1+Inputs!$B$13)^Inputs!$B$12-(1+Inputs!$B$13))/Inputs!$B$13)) -> 396560 | I20: =G20+H20 -> 1150700 | J20: =I20/Inputs!$B$12 -> 230140 | K20: =I20/Inputs!$B$12/Inputs!$B$6 -> 460.28 | L20: =RANK(I20,$I$5:$I$25,1) -> 2 | M20: =RANK(I20,$I$16:$I$25,1) -> 1 | N20: Legacy reference only
A21: Tableau Cloud + Snowflake Azure | B21: Standard role-based | C21: ='License Calculator'!F9 -> 125100 | D21: ='Architecture Costs'!H7 -> 56850 | E21: =Inputs!$B$11*Inputs!$B$47 -> 675000 | F21: =Inputs!$B$50 -> 25000 | G21: =SUM(C21:F21) -> 881950 | H21: =IF(Inputs!$B$13=0,(C21+D21)*(Inputs!$B$12-1),(C21+D21)*(((1+Inputs!$B$13)^Inputs!$B$12-(1+Inputs!$B$13))/Inputs!$B$13)) -> 727800 | I21: =G21+H21 -> 1609750 | J21: =I21/Inputs!$B$12 -> 321950 | K21: =I21/Inputs!$B$12/Inputs!$B$6 -> 643.9 | L21: =RANK(I21,$I$5:$I$25,1) -> 15 | M21: =RANK(I21,$I$16:$I$25,1) -> 8 | N21: Cross-cloud SaaS (AWS to Azure)
A22: Tableau Cloud + Snowflake Azure | B22: Tableau+ (AI tier) | C22: ='License Calculator'!F10 -> 265500 | D22: ='Architecture Costs'!H7 -> 56850 | E22: =Inputs!$B$11*Inputs!$B$47 -> 675000 | F22: =Inputs!$B$50 -> 25000 | G22: =SUM(C22:F22) -> 1022350 | H22: =IF(Inputs!$B$13=0,(C22+D22)*(Inputs!$B$12-1),(C22+D22)*(((1+Inputs!$B$13)^Inputs!$B$12-(1+Inputs!$B$13))/Inputs!$B$13)) -> 1289400 | I22: =G22+H22 -> 2311750 | J22: =I22/Inputs!$B$12 -> 462350 | K22: =I22/Inputs!$B$12/Inputs!$B$6 -> 924.7 | L22: =RANK(I22,$I$5:$I$25,1) -> 20 | M22: =RANK(I22,$I$16:$I$25,1) -> 10 | N22: Quote-only; floor estimate
A23: Tableau Server + Snowflake Azure | B23: Standard role-based | C23: ='License Calculator'!F9 -> 125100 | D23: ='Architecture Costs'!H9 -> 85800 | E23: =Inputs!$B$11*Inputs!$B$47 -> 675000 | F23: =Inputs!$B$50 -> 25000 | G23: =SUM(C23:F23) -> 910900 | H23: =IF(Inputs!$B$13=0,(C23+D23)*(Inputs!$B$12-1),(C23+D23)*(((1+Inputs!$B$13)^Inputs!$B$12-(1+Inputs!$B$13))/Inputs!$B$13)) -> 843600 | I23: =G23+H23 -> 1754500 | J23: =I23/Inputs!$B$12 -> 350900 | K23: =I23/Inputs!$B$12/Inputs!$B$6 -> 701.8 | L23: =RANK(I23,$I$5:$I$25,1) -> 16 | M23: =RANK(I23,$I$16:$I$25,1) -> 9 | N23: Placement control; higher operations
A24: QuickSight + Snowflake Azure | B24: Standard Author + Reader | C24: ='License Calculator'!F11 -> 32400 | D24: ='Architecture Costs'!H11 -> 57090 | E24: =Inputs!$B$11*Inputs!$B$48 -> 800000 | F24: =Inputs!$B$51 -> 50000 | G24: =SUM(C24:F24) -> 939490 | H24: =IF(Inputs!$B$13=0,(C24+D24)*(Inputs!$B$12-1),(C24+D24)*(((1+Inputs!$B$13)^Inputs!$B$12-(1+Inputs!$B$13))/Inputs!$B$13)) -> 357960 | I24: =G24+H24 -> 1297450 | J24: =I24/Inputs!$B$12 -> 259490 | K24: =I24/Inputs!$B$12/Inputs!$B$6 -> 518.98 | L24: =RANK(I24,$I$5:$I$25,1) -> 6 | M24: =RANK(I24,$I$16:$I$25,1) -> 4 | N24: Cross-cloud QuickSight pattern
A25: QuickSight + Snowflake Azure | B25: Author Pro + Q (AI) | C25: ='License Calculator'!F12 -> 45000 | D25: ='Architecture Costs'!H11 -> 57090 | E25: =Inputs!$B$11*Inputs!$B$48 -> 800000 | F25: =Inputs!$B$51 -> 50000 | G25: =SUM(C25:F25) -> 952090 | H25: =IF(Inputs!$B$13=0,(C25+D25)*(Inputs!$B$12-1),(C25+D25)*(((1+Inputs!$B$13)^Inputs!$B$12-(1+Inputs!$B$13))/Inputs!$B$13)) -> 408360 | I25: =G25+H25 -> 1360450 | J25: =I25/Inputs!$B$12 -> 272090 | K25: =I25/Inputs!$B$12/Inputs!$B$6 -> 544.18 | L25: =RANK(I25,$I$5:$I$25,1) -> 10 | M25: =RANK(I25,$I$16:$I$25,1) -> 6 | N25: Cross-cloud with Pro authors
A27: Key: gold = recommended Power BI licensing model; rose = AI-tier rows.

Sheet Scenario Simulator
A1: Scenario Simulator - all 20 configurations x Small / Medium / Large
A2: Edit the blue scenario parameters. Large = Inputs baseline. Incremental cross-cloud compute is scaled by consumers / baseline consumers; operations, gateway and base Snowflake credits are held constant.
A4: Scenario parameter | B4: Unit | C4: S1 Small | D4: S2 Medium | E4: S3 Large
A5: Consumers | B5: users | C5: 100 | D5: 250 | E5: =Inputs!$B$6 -> 500
A6: Developers / creators | B6: users | C6: 10 | D6: 15 | E6: =Inputs!$B$7 -> 25
A7: Explorers / analysts | B7: users | C7: 10 | D7: 20 | E7: =Inputs!$B$8 -> 25
A8: Peak concurrency | B8: users | C8: 20 | D8: 50 | E8: =Inputs!$B$9 -> 100
A9: BI result traffic | B9: TB/month | C9: 1 | D9: 2 | E9: =Inputs!$B$10 -> 5
A10: Reports in migration scope | B10: count | C10: 60 | D10: 140 | E10: =Inputs!$B$11 -> 250
A11: S3 Large links to Inputs (green) so it always reconciles to the TCO Comparison.
C12: S1 Small | F12: S2 Medium | I12: S3 Large (baseline)
A13: Configuration | B13: Licence model | C13: Annual licensing | D13: Annual arch & ops | E13: 5-year TCO | F13: Annual licensing | G13: Annual arch & ops | H13: 5-year TCO | I13: Annual licensing | J13: Annual arch & ops | K13: 5-year TCO
A14: Snowflake on AWS
A15: Power BI + Snowflake AWS | B15: Pro - all named | C15: =($C$6*Inputs!$B$17*12)+($C$7*Inputs!$B$17*12)+($C$5*Inputs!$B$17*12)+(0) -> 20160 | D15: =($C$9*1000*12*Inputs!$B$55)+(Inputs!$B$59*($C$5/Inputs!$B$6))+(Inputs!$B$41)+(Inputs!$B$42+Inputs!$B$63)+(Inputs!$B$66*12*Inputs!$B$36) -> 50280 | E15: =C15+D15+$C$10*Inputs!$B$46+Inputs!$B$49+IF(Inputs!$B$13=0,(C15+D15)*(Inputs!$B$12-1),(C15+D15)*(((1+Inputs!$B$13)^Inputs!$B$12-(1+Inputs!$B$13))/Inputs!$B$13)) -> 532200 | F15: =($D$6*Inputs!$B$17*12)+($D$7*Inputs!$B$17*12)+($D$5*Inputs!$B$17*12)+(0) -> 47880 | G15: =($D$9*1000*12*Inputs!$B$55)+(Inputs!$B$59*($D$5/Inputs!$B$6))+(Inputs!$B$41)+(Inputs!$B$42+Inputs!$B$63)+(Inputs!$B$66*12*Inputs!$B$36) -> 54960 | H15: =F15+G15+$D$10*Inputs!$B$46+Inputs!$B$49+IF(Inputs!$B$13=0,(F15+G15)*(Inputs!$B$12-1),(F15+G15)*(((1+Inputs!$B$13)^Inputs!$B$12-(1+Inputs!$B$13))/Inputs!$B$13)) -> 894200 | I15: =($E$6*Inputs!$B$17*12)+($E$7*Inputs!$B$17*12)+($E$5*Inputs!$B$17*12)+(0) -> 92400 | J15: =($E$9*1000*12*Inputs!$B$55)+(Inputs!$B$59*($E$5/Inputs!$B$6))+(Inputs!$B$41)+(Inputs!$B$42+Inputs!$B$63)+(Inputs!$B$66*12*Inputs!$B$36) -> 64200 | K15: =I15+J15+$E$10*Inputs!$B$46+Inputs!$B$49+IF(Inputs!$B$13=0,(I15+J15)*(Inputs!$B$12-1),(I15+J15)*(((1+Inputs!$B$13)^Inputs!$B$12-(1+Inputs!$B$13))/Inputs!$B$13)) -> 1438000
A16: Power BI + Snowflake AWS | B16: PPU - all named | C16: =($C$6*Inputs!$B$18*12)+($C$7*Inputs!$B$18*12)+($C$5*Inputs!$B$18*12)+(0) -> 34560 | D16: =($C$9*1000*12*Inputs!$B$55)+(Inputs!$B$59*($C$5/Inputs!$B$6))+(Inputs!$B$41)+(Inputs!$B$42+Inputs!$B$63)+(Inputs!$B$66*12*Inputs!$B$36) -> 50280 | E16: =C16+D16+$C$10*Inputs!$B$46+Inputs!$B$49+IF(Inputs!$B$13=0,(C16+D16)*(Inputs!$B$12-1),(C16+D16)*(((1+Inputs!$B$13)^Inputs!$B$12-(1+Inputs!$B$13))/Inputs!$B$13)) -> 604200 | F16: =($D$6*Inputs!$B$18*12)+($D$7*Inputs!$B$18*12)+($D$5*Inputs!$B$18*12)+(0) -> 82080 | G16: =($D$9*1000*12*Inputs!$B$55)+(Inputs!$B$59*($D$5/Inputs!$B$6))+(Inputs!$B$41)+(Inputs!$B$42+Inputs!$B$63)+(Inputs!$B$66*12*Inputs!$B$36) -> 54960 | H16: =F16+G16+$D$10*Inputs!$B$46+Inputs!$B$49+IF(Inputs!$B$13=0,(F16+G16)*(Inputs!$B$12-1),(F16+G16)*(((1+Inputs!$B$13)^Inputs!$B$12-(1+Inputs!$B$13))/Inputs!$B$13)) -> 1065200 | I16: =($E$6*Inputs!$B$18*12)+($E$7*Inputs!$B$18*12)+($E$5*Inputs!$B$18*12)+(0) -> 158400 | J16: =($E$9*1000*12*Inputs!$B$55)+(Inputs!$B$59*($E$5/Inputs!$B$6))+(Inputs!$B$41)+(Inputs!$B$42+Inputs!$B$63)+(Inputs!$B$66*12*Inputs!$B$36) -> 64200 | K16: =I16+J16+$E$10*Inputs!$B$46+Inputs!$B$49+IF(Inputs!$B$13=0,(I16+J16)*(Inputs!$B$12-1),(I16+J16)*(((1+Inputs!$B$13)^Inputs!$B$12-(1+Inputs!$B$13))/Inputs!$B$13)) -> 1768000
A17: Power BI + Snowflake AWS | B17: Fabric F64 Reserved + Pro | C17: =($C$6*Inputs!$B$17*12)+($C$7*Inputs!$B$17*12)+(0)+(Inputs!$B$34*12) -> 63392.04 | D17: =($C$9*1000*12*Inputs!$B$55)+(Inputs!$B$59*($C$5/Inputs!$B$6))+(Inputs!$B$41)+(Inputs!$B$42+Inputs!$B$63)+(Inputs!$B$66*12*Inputs!$B$36) -> 50280 | E17: =C17+D17+$C$10*Inputs!$B$46+Inputs!$B$49+IF(Inputs!$B$13=0,(C17+D17)*(Inputs!$B$12-1),(C17+D17)*(((1+Inputs!$B$13)^Inputs!$B$12-(1+Inputs!$B$13))/Inputs!$B$13)) -> 748360.2 | F17: =($D$6*Inputs!$B$17*12)+($D$7*Inputs!$B$17*12)+(0)+(Inputs!$B$34*12) -> 65912.04 | G17: =($D$9*1000*12*Inputs!$B$55)+(Inputs!$B$59*($D$5/Inputs!$B$6))+(Inputs!$B$41)+(Inputs!$B$42+Inputs!$B$63)+(Inputs!$B$66*12*Inputs!$B$36) -> 54960 | H17: =F17+G17+$D$10*Inputs!$B$46+Inputs!$B$49+IF(Inputs!$B$13=0,(F17+G17)*(Inputs!$B$12-1),(F17+G17)*(((1+Inputs!$B$13)^Inputs!$B$12-(1+Inputs!$B$13))/Inputs!$B$13)) -> 984360.2 | I17: =($E$6*Inputs!$B$17*12)+($E$7*Inputs!$B$17*12)+(0)+(Inputs!$B$34*12) -> 68432.04 | J17: =($E$9*1000*12*Inputs!$B$55)+(Inputs!$B$59*($E$5/Inputs!$B$6))+(Inputs!$B$41)+(Inputs!$B$42+Inputs!$B$63)+(Inputs!$B$66*12*Inputs!$B$36) -> 64200 | K17: =I17+J17+$E$10*Inputs!$B$46+Inputs!$B$49+IF(Inputs!$B$13=0,(I17+J17)*(Inputs!$B$12-1),(I17+J17)*(((1+Inputs!$B$13)^Inputs!$B$12-(1+Inputs!$B$13))/Inputs!$B$13)) -> 1318160.2
A18: Power BI + Snowflake AWS | B18: Fabric F64 PAYG + Pro | C18: =($C$6*Inputs!$B$17*12)+($C$7*Inputs!$B$17*12)+(0)+(Inputs!$B$33*12) -> 104275.2 | D18: =($C$9*1000*12*Inputs!$B$55)+(Inputs!$B$59*($C$5/Inputs!$B$6))+(Inputs!$B$41)+(Inputs!$B$42+Inputs!$B$63)+(Inputs!$B$66*12*Inputs!$B$36) -> 50280 | E18: =C18+D18+$C$10*Inputs!$B$46+Inputs!$B$49+IF(Inputs!$B$13=0,(C18+D18)*(Inputs!$B$12-1),(C18+D18)*(((1+Inputs!$B$13)^Inputs!$B$12-(1+Inputs!$B$13))/Inputs!$B$13)) -> 952776 | F18: =($D$6*Inputs!$B$17*12)+($D$7*Inputs!$B$17*12)+(0)+(Inputs!$B$33*12) -> 106795.2 | G18: =($D$9*1000*12*Inputs!$B$55)+(Inputs!$B$59*($D$5/Inputs!$B$6))+(Inputs!$B$41)+(Inputs!$B$42+Inputs!$B$63)+(Inputs!$B$66*12*Inputs!$B$36) -> 54960 | H18: =F18+G18+$D$10*Inputs!$B$46+Inputs!$B$49+IF(Inputs!$B$13=0,(F18+G18)*(Inputs!$B$12-1),(F18+G18)*(((1+Inputs!$B$13)^Inputs!$B$12-(1+Inputs!$B$13))/Inputs!$B$13)) -> 1188776 | I18: =($E$6*Inputs!$B$17*12)+($E$7*Inputs!$B$17*12)+(0)+(Inputs!$B$33*12) -> 109315.2 | J18: =($E$9*1000*12*Inputs!$B$55)+(Inputs!$B$59*($E$5/Inputs!$B$6))+(Inputs!$B$41)+(Inputs!$B$42+Inputs!$B$63)+(Inputs!$B$66*12*Inputs!$B$36) -> 64200 | K18: =I18+J18+$E$10*Inputs!$B$46+Inputs!$B$49+IF(Inputs!$B$13=0,(I18+J18)*(Inputs!$B$12-1),(I18+J18)*(((1+Inputs!$B$13)^Inputs!$B$12-(1+Inputs!$B$13))/Inputs!$B$13)) -> 1522576
A19: Power BI + Snowflake AWS | B19: Premium P1 + Pro | C19: =($C$6*Inputs!$B$17*12)+($C$7*Inputs!$B$17*12)+(0)+(Inputs!$B$35*12) -> 63300 | D19: =($C$9*1000*12*Inputs!$B$55)+(Inputs!$B$59*($C$5/Inputs!$B$6))+(Inputs!$B$41)+(Inputs!$B$42+Inputs!$B$63)+(Inputs!$B$66*12*Inputs!$B$36) -> 50280 | E19: =C19+D19+$C$10*Inputs!$B$46+Inputs!$B$49+IF(Inputs!$B$13=0,(C19+D19)*(Inputs!$B$12-1),(C19+D19)*(((1+Inputs!$B$13)^Inputs!$B$12-(1+Inputs!$B$13))/Inputs!$B$13)) -> 747900 | F19: =($D$6*Inputs!$B$17*12)+($D$7*Inputs!$B$17*12)+(0)+(Inputs!$B$35*12) -> 65820 | G19: =($D$9*1000*12*Inputs!$B$55)+(Inputs!$B$59*($D$5/Inputs!$B$6))+(Inputs!$B$41)+(Inputs!$B$42+Inputs!$B$63)+(Inputs!$B$66*12*Inputs!$B$36) -> 54960 | H19: =F19+G19+$D$10*Inputs!$B$46+Inputs!$B$49+IF(Inputs!$B$13=0,(F19+G19)*(Inputs!$B$12-1),(F19+G19)*(((1+Inputs!$B$13)^Inputs!$B$12-(1+Inputs!$B$13))/Inputs!$B$13)) -> 983900 | I19: =($E$6*Inputs!$B$17*12)+($E$7*Inputs!$B$17*12)+(0)+(Inputs!$B$35*12) -> 68340 | J19: =($E$9*1000*12*Inputs!$B$55)+(Inputs!$B$59*($E$5/Inputs!$B$6))+(Inputs!$B$41)+(Inputs!$B$42+Inputs!$B$63)+(Inputs!$B$66*12*Inputs!$B$36) -> 64200 | K19: =I19+J19+$E$10*Inputs!$B$46+Inputs!$B$49+IF(Inputs!$B$13=0,(I19+J19)*(Inputs!$B$12-1),(I19+J19)*(((1+Inputs!$B$13)^Inputs!$B$12-(1+Inputs!$B$13))/Inputs!$B$13)) -> 1317700
A20: Tableau Cloud + Snowflake AWS | B20: Standard role-based | C20: =($C$6*Inputs!$B$19*12)+($C$7*Inputs!$B$20*12)+($C$5*Inputs!$B$21*12)+(0) -> 32040 | D20: =($C$9*1000*12*Inputs!$B$55*Inputs!$B$61)+(Inputs!$B$59*Inputs!$B$61*($C$5/Inputs!$B$6))+(0)+(Inputs!$B$43+IF(Inputs!$B$61>0,Inputs!$B$64,0))+(Inputs!$B$67*12*Inputs!$B$36) -> 35800 | E20: =C20+D20+$C$10*Inputs!$B$47+Inputs!$B$50+IF(Inputs!$B$13=0,(C20+D20)*(Inputs!$B$12-1),(C20+D20)*(((1+Inputs!$B$13)^Inputs!$B$12-(1+Inputs!$B$13))/Inputs!$B$13)) -> 526200 | F20: =($D$6*Inputs!$B$19*12)+($D$7*Inputs!$B$20*12)+($D$5*Inputs!$B$21*12)+(0) -> 68580 | G20: =($D$9*1000*12*Inputs!$B$55*Inputs!$B$61)+(Inputs!$B$59*Inputs!$B$61*($D$5/Inputs!$B$6))+(0)+(Inputs!$B$43+IF(Inputs!$B$61>0,Inputs!$B$64,0))+(Inputs!$B$67*12*Inputs!$B$36) -> 35800 | H20: =F20+G20+$D$10*Inputs!$B$47+Inputs!$B$50+IF(Inputs!$B$13=0,(F20+G20)*(Inputs!$B$12-1),(F20+G20)*(((1+Inputs!$B$13)^Inputs!$B$12-(1+Inputs!$B$13))/Inputs!$B$13)) -> 924900 | I20: =($E$6*Inputs!$B$19*12)+($E$7*Inputs!$B$20*12)+($E$5*Inputs!$B$21*12)+(0) -> 125100 | J20: =($E$9*1000*12*Inputs!$B$55*Inputs!$B$61)+(Inputs!$B$59*Inputs!$B$61*($E$5/Inputs!$B$6))+(0)+(Inputs!$B$43+IF(Inputs!$B$61>0,Inputs!$B$64,0))+(Inputs!$B$67*12*Inputs!$B$36) -> 35800 | K20: =I20+J20+$E$10*Inputs!$B$47+Inputs!$B$50+IF(Inputs!$B$13=0,(I20+J20)*(Inputs!$B$12-1),(I20+J20)*(((1+Inputs!$B$13)^Inputs!$B$12-(1+Inputs!$B$13))/Inputs!$B$13)) -> 1504500
A21: Tableau Cloud + Snowflake AWS | B21: Tableau+ (AI tier) | C21: =($C$6*Inputs!$B$22*12)+($C$7*Inputs!$B$23*12)+($C$5*Inputs!$B$24*12)+(0) -> 64200 | D21: =($C$9*1000*12*Inputs!$B$55*Inputs!$B$61)+(Inputs!$B$59*Inputs!$B$61*($C$5/Inputs!$B$6))+(0)+(Inputs!$B$43+IF(Inputs!$B$61>0,Inputs!$B$64,0))+(Inputs!$B$67*12*Inputs!$B$36) -> 35800 | E21: =C21+D21+$C$10*Inputs!$B$47+Inputs!$B$50+IF(Inputs!$B$13=0,(C21+D21)*(Inputs!$B$12-1),(C21+D21)*(((1+Inputs!$B$13)^Inputs!$B$12-(1+Inputs!$B$13))/Inputs!$B$13)) -> 687000 | F21: =($D$6*Inputs!$B$22*12)+($D$7*Inputs!$B$23*12)+($D$5*Inputs!$B$24*12)+(0) -> 142500 | G21: =($D$9*1000*12*Inputs!$B$55*Inputs!$B$61)+(Inputs!$B$59*Inputs!$B$61*($D$5/Inputs!$B$6))+(0)+(Inputs!$B$43+IF(Inputs!$B$61>0,Inputs!$B$64,0))+(Inputs!$B$67*12*Inputs!$B$36) -> 35800 | H21: =F21+G21+$D$10*Inputs!$B$47+Inputs!$B$50+IF(Inputs!$B$13=0,(F21+G21)*(Inputs!$B$12-1),(F21+G21)*(((1+Inputs!$B$13)^Inputs!$B$12-(1+Inputs!$B$13))/Inputs!$B$13)) -> 1294500 | I21: =($E$6*Inputs!$B$22*12)+($E$7*Inputs!$B$23*12)+($E$5*Inputs!$B$24*12)+(0) -> 265500 | J21: =($E$9*1000*12*Inputs!$B$55*Inputs!$B$61)+(Inputs!$B$59*Inputs!$B$61*($E$5/Inputs!$B$6))+(0)+(Inputs!$B$43+IF(Inputs!$B$61>0,Inputs!$B$64,0))+(Inputs!$B$67*12*Inputs!$B$36) -> 35800 | K21: =I21+J21+$E$10*Inputs!$B$47+Inputs!$B$50+IF(Inputs!$B$13=0,(I21+J21)*(Inputs!$B$12-1),(I21+J21)*(((1+Inputs!$B$13)^Inputs!$B$12-(1+Inputs!$B$13))/Inputs!$B$13)) -> 2206500
A22: Tableau Server + Snowflake AWS | B22: Standard role-based | C22: =($C$6*Inputs!$B$19*12)+($C$7*Inputs!$B$20*12)+($C$5*Inputs!$B$21*12)+(0) -> 32040 | D22: =(0)+(0)+(Inputs!$B$40)+(Inputs!$B$44)+(Inputs!$B$67*12*Inputs!$B$36) -> 85800 | E22: =C22+D22+$C$10*Inputs!$B$47+Inputs!$B$50+IF(Inputs!$B$13=0,(C22+D22)*(Inputs!$B$12-1),(C22+D22)*(((1+Inputs!$B$13)^Inputs!$B$12-(1+Inputs!$B$13))/Inputs!$B$13)) -> 776200 | F22: =($D$6*Inputs!$B$19*12)+($D$7*Inputs!$B$20*12)+($D$5*Inputs!$B$21*12)+(0) -> 68580 | G22: =(0)+(0)+(Inputs!$B$40)+(Inputs!$B$44)+(Inputs!$B$67*12*Inputs!$B$36) -> 85800 | H22: =F22+G22+$D$10*Inputs!$B$47+Inputs!$B$50+IF(Inputs!$B$13=0,(F22+G22)*(Inputs!$B$12-1),(F22+G22)*(((1+Inputs!$B$13)^Inputs!$B$12-(1+Inputs!$B$13))/Inputs!$B$13)) -> 1174900 | I22: =($E$6*Inputs!$B$19*12)+($E$7*Inputs!$B$20*12)+($E$5*Inputs!$B$21*12)+(0) -> 125100 | J22: =(0)+(0)+(Inputs!$B$40)+(Inputs!$B$44)+(Inputs!$B$67*12*Inputs!$B$36) -> 85800 | K22: =I22+J22+$E$10*Inputs!$B$47+Inputs!$B$50+IF(Inputs!$B$13=0,(I22+J22)*(Inputs!$B$12-1),(I22+J22)*(((1+Inputs!$B$13)^Inputs!$B$12-(1+Inputs!$B$13))/Inputs!$B$13)) -> 1754500
A23: QuickSight + Snowflake AWS | B23: Standard Author + Reader | C23: =($C$6*Inputs!$B$25*12)+($C$7*Inputs!$B$25*12)+($C$5*Inputs!$B$27*12)+(0) -> 9360 | D23: =(0)+(0)+(0)+(Inputs!$B$45)+(Inputs!$B$68*12*Inputs!$B$36) -> 25080 | E23: =C23+D23+$C$10*Inputs!$B$48+Inputs!$B$51+IF(Inputs!$B$13=0,(C23+D23)*(Inputs!$B$12-1),(C23+D23)*(((1+Inputs!$B$13)^Inputs!$B$12-(1+Inputs!$B$13))/Inputs!$B$13)) -> 414200 | F23: =($D$6*Inputs!$B$25*12)+($D$7*Inputs!$B$25*12)+($D$5*Inputs!$B$27*12)+(0) -> 19080 | G23: =(0)+(0)+(0)+(Inputs!$B$45)+(Inputs!$B$68*12*Inputs!$B$36) -> 25080 | H23: =F23+G23+$D$10*Inputs!$B$48+Inputs!$B$51+IF(Inputs!$B$13=0,(F23+G23)*(Inputs!$B$12-1),(F23+G23)*(((1+Inputs!$B$13)^Inputs!$B$12-(1+Inputs!$B$13))/Inputs!$B$13)) -> 718800 | I23: =($E$6*Inputs!$B$25*12)+($E$7*Inputs!$B$25*12)+($E$5*Inputs!$B$27*12)+(0) -> 32400 | J23: =(0)+(0)+(0)+(Inputs!$B$45)+(Inputs!$B$68*12*Inputs!$B$36) -> 25080 | K23: =I23+J23+$E$10*Inputs!$B$48+Inputs!$B$51+IF(Inputs!$B$13=0,(I23+J23)*(Inputs!$B$12-1),(I23+J23)*(((1+Inputs!$B$13)^Inputs!$B$12-(1+Inputs!$B$13))/Inputs!$B$13)) -> 1137400
A24: QuickSight + Snowflake AWS | B24: Author Pro + Q (AI) | C24: =($C$6*Inputs!$B$26*12)+($C$7*Inputs!$B$26*12)+($C$5*Inputs!$B$27*12)+(Inputs!$B$29*12) -> 16200 | D24: =(0)+(0)+(0)+(Inputs!$B$45)+(Inputs!$B$68*12*Inputs!$B$36) -> 25080 | E24: =C24+D24+$C$10*Inputs!$B$48+Inputs!$B$51+IF(Inputs!$B$13=0,(C24+D24)*(Inputs!$B$12-1),(C24+D24)*(((1+Inputs!$B$13)^Inputs!$B$12-(1+Inputs!$B$13))/Inputs!$B$13)) -> 448400 | F24: =($D$6*Inputs!$B$26*12)+($D$7*Inputs!$B$26*12)+($D$5*Inputs!$B$27*12)+(Inputs!$B$29*12) -> 28800 | G24: =(0)+(0)+(0)+(Inputs!$B$45)+(Inputs!$B$68*12*Inputs!$B$36) -> 25080 | H24: =F24+G24+$D$10*Inputs!$B$48+Inputs!$B$51+IF(Inputs!$B$13=0,(F24+G24)*(Inputs!$B$12-1),(F24+G24)*(((1+Inputs!$B$13)^Inputs!$B$12-(1+Inputs!$B$13))/Inputs!$B$13)) -> 767400 | I24: =($E$6*Inputs!$B$26*12)+($E$7*Inputs!$B$26*12)+($E$5*Inputs!$B$27*12)+(Inputs!$B$29*12) -> 45000 | J24: =(0)+(0)+(0)+(Inputs!$B$45)+(Inputs!$B$68*12*Inputs!$B$36) -> 25080 | K24: =I24+J24+$E$10*Inputs!$B$48+Inputs!$B$51+IF(Inputs!$B$13=0,(I24+J24)*(Inputs!$B$12-1),(I24+J24)*(((1+Inputs!$B$13)^Inputs!$B$12-(1+Inputs!$B$13))/Inputs!$B$13)) -> 1200400
A25: Snowflake on Azure
A26: Power BI + Snowflake Azure | B26: Pro - all named | C26: =($C$6*Inputs!$B$17*12)+($C$7*Inputs!$B$17*12)+($C$5*Inputs!$B$17*12)+(0) -> 20160 | D26: =(0)+(0)+(0)+(Inputs!$B$42)+(Inputs!$B$66*12*Inputs!$B$36) -> 30800 | E26: =C26+D26+$C$10*Inputs!$B$46+Inputs!$B$49+IF(Inputs!$B$13=0,(C26+D26)*(Inputs!$B$12-1),(C26+D26)*(((1+Inputs!$B$13)^Inputs!$B$12-(1+Inputs!$B$13))/Inputs!$B$13)) -> 434800 | F26: =($D$6*Inputs!$B$17*12)+($D$7*Inputs!$B$17*12)+($D$5*Inputs!$B$17*12)+(0) -> 47880 | G26: =(0)+(0)+(0)+(Inputs!$B$42)+(Inputs!$B$66*12*Inputs!$B$36) -> 30800 | H26: =F26+G26+$D$10*Inputs!$B$46+Inputs!$B$49+IF(Inputs!$B$13=0,(F26+G26)*(Inputs!$B$12-1),(F26+G26)*(((1+Inputs!$B$13)^Inputs!$B$12-(1+Inputs!$B$13))/Inputs!$B$13)) -> 773400 | I26: =($E$6*Inputs!$B$17*12)+($E$7*Inputs!$B$17*12)+($E$5*Inputs!$B$17*12)+(0) -> 92400 | J26: =(0)+(0)+(0)+(Inputs!$B$42)+(Inputs!$B$66*12*Inputs!$B$36) -> 30800 | K26: =I26+J26+$E$10*Inputs!$B$46+Inputs!$B$49+IF(Inputs!$B$13=0,(I26+J26)*(Inputs!$B$12-1),(I26+J26)*(((1+Inputs!$B$13)^Inputs!$B$12-(1+Inputs!$B$13))/Inputs!$B$13)) -> 1271000
A27: Power BI + Snowflake Azure | B27: PPU - all named | C27: =($C$6*Inputs!$B$18*12)+($C$7*Inputs!$B$18*12)+($C$5*Inputs!$B$18*12)+(0) -> 34560 | D27: =(0)+(0)+(0)+(Inputs!$B$42)+(Inputs!$B$66*12*Inputs!$B$36) -> 30800 | E27: =C27+D27+$C$10*Inputs!$B$46+Inputs!$B$49+IF(Inputs!$B$13=0,(C27+D27)*(Inputs!$B$12-1),(C27+D27)*(((1+Inputs!$B$13)^Inputs!$B$12-(1+Inputs!$B$13))/Inputs!$B$13)) -> 506800 | F27: =($D$6*Inputs!$B$18*12)+($D$7*Inputs!$B$18*12)+($D$5*Inputs!$B$18*12)+(0) -> 82080 | G27: =(0)+(0)+(0)+(Inputs!$B$42)+(Inputs!$B$66*12*Inputs!$B$36) -> 30800 | H27: =F27+G27+$D$10*Inputs!$B$46+Inputs!$B$49+IF(Inputs!$B$13=0,(F27+G27)*(Inputs!$B$12-1),(F27+G27)*(((1+Inputs!$B$13)^Inputs!$B$12-(1+Inputs!$B$13))/Inputs!$B$13)) -> 944400 | I27: =($E$6*Inputs!$B$18*12)+($E$7*Inputs!$B$18*12)+($E$5*Inputs!$B$18*12)+(0) -> 158400 | J27: =(0)+(0)+(0)+(Inputs!$B$42)+(Inputs!$B$66*12*Inputs!$B$36) -> 30800 | K27: =I27+J27+$E$10*Inputs!$B$46+Inputs!$B$49+IF(Inputs!$B$13=0,(I27+J27)*(Inputs!$B$12-1),(I27+J27)*(((1+Inputs!$B$13)^Inputs!$B$12-(1+Inputs!$B$13))/Inputs!$B$13)) -> 1601000
A28: Power BI + Snowflake Azure | B28: Fabric F64 Reserved + Pro | C28: =($C$6*Inputs!$B$17*12)+($C$7*Inputs!$B$17*12)+(0)+(Inputs!$B$34*12) -> 63392.04 | D28: =(0)+(0)+(0)+(Inputs!$B$42)+(Inputs!$B$66*12*Inputs!$B$36) -> 30800 | E28: =C28+D28+$C$10*Inputs!$B$46+Inputs!$B$49+IF(Inputs!$B$13=0,(C28+D28)*(Inputs!$B$12-1),(C28+D28)*(((1+Inputs!$B$13)^Inputs!$B$12-(1+Inputs!$B$13))/Inputs!$B$13)) -> 650960.2 | F28: =($D$6*Inputs!$B$17*12)+($D$7*Inputs!$B$17*12)+(0)+(Inputs!$B$34*12) -> 65912.04 | G28: =(0)+(0)+(0)+(Inputs!$B$42)+(Inputs!$B$66*12*Inputs!$B$36) -> 30800 | H28: =F28+G28+$D$10*Inputs!$B$46+Inputs!$B$49+IF(Inputs!$B$13=0,(F28+G28)*(Inputs!$B$12-1),(F28+G28)*(((1+Inputs!$B$13)^Inputs!$B$12-(1+Inputs!$B$13))/Inputs!$B$13)) -> 863560.2 | I28: =($E$6*Inputs!$B$17*12)+($E$7*Inputs!$B$17*12)+(0)+(Inputs!$B$34*12) -> 68432.04 | J28: =(0)+(0)+(0)+(Inputs!$B$42)+(Inputs!$B$66*12*Inputs!$B$36) -> 30800 | K28: =I28+J28+$E$10*Inputs!$B$46+Inputs!$B$49+IF(Inputs!$B$13=0,(I28+J28)*(Inputs!$B$12-1),(I28+J28)*(((1+Inputs!$B$13)^Inputs!$B$12-(1+Inputs!$B$13))/Inputs!$B$13)) -> 1151160.2
A29: Power BI + Snowflake Azure | B29: Fabric F64 PAYG + Pro | C29: =($C$6*Inputs!$B$17*12)+($C$7*Inputs!$B$17*12)+(0)+(Inputs!$B$33*12) -> 104275.2 | D29: =(0)+(0)+(0)+(Inputs!$B$42)+(Inputs!$B$66*12*Inputs!$B$36) -> 30800 | E29: =C29+D29+$C$10*Inputs!$B$46+Inputs!$B$49+IF(Inputs!$B$13=0,(C29+D29)*(Inputs!$B$12-1),(C29+D29)*(((1+Inputs!$B$13)^Inputs!$B$12-(1+Inputs!$B$13))/Inputs!$B$13)) -> 855376 | F29: =($D$6*Inputs!$B$17*12)+($D$7*Inputs!$B$17*12)+(0)+(Inputs!$B$33*12) -> 106795.2 | G29: =(0)+(0)+(0)+(Inputs!$B$42)+(Inputs!$B$66*12*Inputs!$B$36) -> 30800 | H29: =F29+G29+$D$10*Inputs!$B$46+Inputs!$B$49+IF(Inputs!$B$13=0,(F29+G29)*(Inputs!$B$12-1),(F29+G29)*(((1+Inputs!$B$13)^Inputs!$B$12-(1+Inputs!$B$13))/Inputs!$B$13)) -> 1067976 | I29: =($E$6*Inputs!$B$17*12)+($E$7*Inputs!$B$17*12)+(0)+(Inputs!$B$33*12) -> 109315.2 | J29: =(0)+(0)+(0)+(Inputs!$B$42)+(Inputs!$B$66*12*Inputs!$B$36) -> 30800 | K29: =I29+J29+$E$10*Inputs!$B$46+Inputs!$B$49+IF(Inputs!$B$13=0,(I29+J29)*(Inputs!$B$12-1),(I29+J29)*(((1+Inputs!$B$13)^Inputs!$B$12-(1+Inputs!$B$13))/Inputs!$B$13)) -> 1355576
A30: Power BI + Snowflake Azure | B30: Premium P1 + Pro | C30: =($C$6*Inputs!$B$17*12)+($C$7*Inputs!$B$17*12)+(0)+(Inputs!$B$35*12) -> 63300 | D30: =(0)+(0)+(0)+(Inputs!$B$42)+(Inputs!$B$66*12*Inputs!$B$36) -> 30800 | E30: =C30+D30+$C$10*Inputs!$B$46+Inputs!$B$49+IF(Inputs!$B$13=0,(C30+D30)*(Inputs!$B$12-1),(C30+D30)*(((1+Inputs!$B$13)^Inputs!$B$12-(1+Inputs!$B$13))/Inputs!$B$13)) -> 650500 | F30: =($D$6*Inputs!$B$17*12)+($D$7*Inputs!$B$17*12)+(0)+(Inputs!$B$35*12) -> 65820 | G30: =(0)+(0)+(0)+(Inputs!$B$42)+(Inputs!$B$66*12*Inputs!$B$36) -> 30800 | H30: =F30+G30+$D$10*Inputs!$B$46+Inputs!$B$49+IF(Inputs!$B$13=0,(F30+G30)*(Inputs!$B$12-1),(F30+G30)*(((1+Inputs!$B$13)^Inputs!$B$12-(1+Inputs!$B$13))/Inputs!$B$13)) -> 863100 | I30: =($E$6*Inputs!$B$17*12)+($E$7*Inputs!$B$17*12)+(0)+(Inputs!$B$35*12) -> 68340 | J30: =(0)+(0)+(0)+(Inputs!$B$42)+(Inputs!$B$66*12*Inputs!$B$36) -> 30800 | K30: =I30+J30+$E$10*Inputs!$B$46+Inputs!$B$49+IF(Inputs!$B$13=0,(I30+J30)*(Inputs!$B$12-1),(I30+J30)*(((1+Inputs!$B$13)^Inputs!$B$12-(1+Inputs!$B$13))/Inputs!$B$13)) -> 1150700
A31: Tableau Cloud + Snowflake Azure | B31: Standard role-based | C31: =($C$6*Inputs!$B$19*12)+($C$7*Inputs!$B$20*12)+($C$5*Inputs!$B$21*12)+(0) -> 32040 | D31: =($C$9*1000*12*Inputs!$B$55*Inputs!$B$60)+(Inputs!$B$59*Inputs!$B$60*($C$5/Inputs!$B$6))+(0)+(Inputs!$B$43+IF(Inputs!$B$60>0,Inputs!$B$64,0))+(Inputs!$B$67*12*Inputs!$B$36) -> 46410 | E31: =C31+D31+$C$10*Inputs!$B$47+Inputs!$B$50+IF(Inputs!$B$13=0,(C31+D31)*(Inputs!$B$12-1),(C31+D31)*(((1+Inputs!$B$13)^Inputs!$B$12-(1+Inputs!$B$13))/Inputs!$B$13)) -> 579250 | F31: =($D$6*Inputs!$B$19*12)+($D$7*Inputs!$B$20*12)+($D$5*Inputs!$B$21*12)+(0) -> 68580 | G31: =($D$9*1000*12*Inputs!$B$55*Inputs!$B$60)+(Inputs!$B$59*Inputs!$B$60*($D$5/Inputs!$B$6))+(0)+(Inputs!$B$43+IF(Inputs!$B$60>0,Inputs!$B$64,0))+(Inputs!$B$67*12*Inputs!$B$36) -> 49920 | H31: =F31+G31+$D$10*Inputs!$B$47+Inputs!$B$50+IF(Inputs!$B$13=0,(F31+G31)*(Inputs!$B$12-1),(F31+G31)*(((1+Inputs!$B$13)^Inputs!$B$12-(1+Inputs!$B$13))/Inputs!$B$13)) -> 995500 | I31: =($E$6*Inputs!$B$19*12)+($E$7*Inputs!$B$20*12)+($E$5*Inputs!$B$21*12)+(0) -> 125100 | J31: =($E$9*1000*12*Inputs!$B$55*Inputs!$B$60)+(Inputs!$B$59*Inputs!$B$60*($E$5/Inputs!$B$6))+(0)+(Inputs!$B$43+IF(Inputs!$B$60>0,Inputs!$B$64,0))+(Inputs!$B$67*12*Inputs!$B$36) -> 56850 | K31: =I31+J31+$E$10*Inputs!$B$47+Inputs!$B$50+IF(Inputs!$B$13=0,(I31+J31)*(Inputs!$B$12-1),(I31+J31)*(((1+Inputs!$B$13)^Inputs!$B$12-(1+Inputs!$B$13))/Inputs!$B$13)) -> 1609750
A32: Tableau Cloud + Snowflake Azure | B32: Tableau+ (AI tier) | C32: =($C$6*Inputs!$B$22*12)+($C$7*Inputs!$B$23*12)+($C$5*Inputs!$B$24*12)+(0) -> 64200 | D32: =($C$9*1000*12*Inputs!$B$55*Inputs!$B$60)+(Inputs!$B$59*Inputs!$B$60*($C$5/Inputs!$B$6))+(0)+(Inputs!$B$43+IF(Inputs!$B$60>0,Inputs!$B$64,0))+(Inputs!$B$67*12*Inputs!$B$36) -> 46410 | E32: =C32+D32+$C$10*Inputs!$B$47+Inputs!$B$50+IF(Inputs!$B$13=0,(C32+D32)*(Inputs!$B$12-1),(C32+D32)*(((1+Inputs!$B$13)^Inputs!$B$12-(1+Inputs!$B$13))/Inputs!$B$13)) -> 740050 | F32: =($D$6*Inputs!$B$22*12)+($D$7*Inputs!$B$23*12)+($D$5*Inputs!$B$24*12)+(0) -> 142500 | G32: =($D$9*1000*12*Inputs!$B$55*Inputs!$B$60)+(Inputs!$B$59*Inputs!$B$60*($D$5/Inputs!$B$6))+(0)+(Inputs!$B$43+IF(Inputs!$B$60>0,Inputs!$B$64,0))+(Inputs!$B$67*12*Inputs!$B$36) -> 49920 | H32: =F32+G32+$D$10*Inputs!$B$47+Inputs!$B$50+IF(Inputs!$B$13=0,(F32+G32)*(Inputs!$B$12-1),(F32+G32)*(((1+Inputs!$B$13)^Inputs!$B$12-(1+Inputs!$B$13))/Inputs!$B$13)) -> 1365100 | I32: =($E$6*Inputs!$B$22*12)+($E$7*Inputs!$B$23*12)+($E$5*Inputs!$B$24*12)+(0) -> 265500 | J32: =($E$9*1000*12*Inputs!$B$55*Inputs!$B$60)+(Inputs!$B$59*Inputs!$B$60*($E$5/Inputs!$B$6))+(0)+(Inputs!$B$43+IF(Inputs!$B$60>0,Inputs!$B$64,0))+(Inputs!$B$67*12*Inputs!$B$36) -> 56850 | K32: =I32+J32+$E$10*Inputs!$B$47+Inputs!$B$50+IF(Inputs!$B$13=0,(I32+J32)*(Inputs!$B$12-1),(I32+J32)*(((1+Inputs!$B$13)^Inputs!$B$12-(1+Inputs!$B$13))/Inputs!$B$13)) -> 2311750
A33: Tableau Server + Snowflake Azure | B33: Standard role-based | C33: =($C$6*Inputs!$B$19*12)+($C$7*Inputs!$B$20*12)+($C$5*Inputs!$B$21*12)+(0) -> 32040 | D33: =(0)+(0)+(Inputs!$B$40)+(Inputs!$B$44)+(Inputs!$B$67*12*Inputs!$B$36) -> 85800 | E33: =C33+D33+$C$10*Inputs!$B$47+Inputs!$B$50+IF(Inputs!$B$13=0,(C33+D33)*(Inputs!$B$12-1),(C33+D33)*(((1+Inputs!$B$13)^Inputs!$B$12-(1+Inputs!$B$13))/Inputs!$B$13)) -> 776200 | F33: =($D$6*Inputs!$B$19*12)+($D$7*Inputs!$B$20*12)+($D$5*Inputs!$B$21*12)+(0) -> 68580 | G33: =(0)+(0)+(Inputs!$B$40)+(Inputs!$B$44)+(Inputs!$B$67*12*Inputs!$B$36) -> 85800 | H33: =F33+G33+$D$10*Inputs!$B$47+Inputs!$B$50+IF(Inputs!$B$13=0,(F33+G33)*(Inputs!$B$12-1),(F33+G33)*(((1+Inputs!$B$13)^Inputs!$B$12-(1+Inputs!$B$13))/Inputs!$B$13)) -> 1174900 | I33: =($E$6*Inputs!$B$19*12)+($E$7*Inputs!$B$20*12)+($E$5*Inputs!$B$21*12)+(0) -> 125100 | J33: =(0)+(0)+(Inputs!$B$40)+(Inputs!$B$44)+(Inputs!$B$67*12*Inputs!$B$36) -> 85800 | K33: =I33+J33+$E$10*Inputs!$B$47+Inputs!$B$50+IF(Inputs!$B$13=0,(I33+J33)*(Inputs!$B$12-1),(I33+J33)*(((1+Inputs!$B$13)^Inputs!$B$12-(1+Inputs!$B$13))/Inputs!$B$13)) -> 1754500
A34: QuickSight + Snowflake Azure | B34: Standard Author + Reader | C34: =($C$6*Inputs!$B$25*12)+($C$7*Inputs!$B$25*12)+($C$5*Inputs!$B$27*12)+(0) -> 9360 | D34: =($C$9*1000*12*Inputs!$B$55*Inputs!$B$62)+(Inputs!$B$59*Inputs!$B$62*($C$5/Inputs!$B$6))+(0)+(Inputs!$B$45+Inputs!$B$65)+(Inputs!$B$68*12*Inputs!$B$36) -> 41082 | E34: =C34+D34+$C$10*Inputs!$B$48+Inputs!$B$51+IF(Inputs!$B$13=0,(C34+D34)*(Inputs!$B$12-1),(C34+D34)*(((1+Inputs!$B$13)^Inputs!$B$12-(1+Inputs!$B$13))/Inputs!$B$13)) -> 494210 | F34: =($D$6*Inputs!$B$25*12)+($D$7*Inputs!$B$25*12)+($D$5*Inputs!$B$27*12)+(0) -> 19080 | G34: =($D$9*1000*12*Inputs!$B$55*Inputs!$B$62)+(Inputs!$B$59*Inputs!$B$62*($D$5/Inputs!$B$6))+(0)+(Inputs!$B$45+Inputs!$B$65)+(Inputs!$B$68*12*Inputs!$B$36) -> 46464 | H34: =F34+G34+$D$10*Inputs!$B$48+Inputs!$B$51+IF(Inputs!$B$13=0,(F34+G34)*(Inputs!$B$12-1),(F34+G34)*(((1+Inputs!$B$13)^Inputs!$B$12-(1+Inputs!$B$13))/Inputs!$B$13)) -> 825720 | I34: =($E$6*Inputs!$B$25*12)+($E$7*Inputs!$B$25*12)+($E$5*Inputs!$B$27*12)+(0) -> 32400 | J34: =($E$9*1000*12*Inputs!$B$55*Inputs!$B$62)+(Inputs!$B$59*Inputs!$B$62*($E$5/Inputs!$B$6))+(0)+(Inputs!$B$45+Inputs!$B$65)+(Inputs!$B$68*12*Inputs!$B$36) -> 57090 | K34: =I34+J34+$E$10*Inputs!$B$48+Inputs!$B$51+IF(Inputs!$B$13=0,(I34+J34)*(Inputs!$B$12-1),(I34+J34)*(((1+Inputs!$B$13)^Inputs!$B$12-(1+Inputs!$B$13))/Inputs!$B$13)) -> 1297450
A35: QuickSight + Snowflake Azure | B35: Author Pro + Q (AI) | C35: =($C$6*Inputs!$B$26*12)+($C$7*Inputs!$B$26*12)+($C$5*Inputs!$B$27*12)+(Inputs!$B$29*12) -> 16200 | D35: =($C$9*1000*12*Inputs!$B$55*Inputs!$B$62)+(Inputs!$B$59*Inputs!$B$62*($C$5/Inputs!$B$6))+(0)+(Inputs!$B$45+Inputs!$B$65)+(Inputs!$B$68*12*Inputs!$B$36) -> 41082 | E35: =C35+D35+$C$10*Inputs!$B$48+Inputs!$B$51+IF(Inputs!$B$13=0,(C35+D35)*(Inputs!$B$12-1),(C35+D35)*(((1+Inputs!$B$13)^Inputs!$B$12-(1+Inputs!$B$13))/Inputs!$B$13)) -> 528410 | F35: =($D$6*Inputs!$B$26*12)+($D$7*Inputs!$B$26*12)+($D$5*Inputs!$B$27*12)+(Inputs!$B$29*12) -> 28800 | G35: =($D$9*1000*12*Inputs!$B$55*Inputs!$B$62)+(Inputs!$B$59*Inputs!$B$62*($D$5/Inputs!$B$6))+(0)+(Inputs!$B$45+Inputs!$B$65)+(Inputs!$B$68*12*Inputs!$B$36) -> 46464 | H35: =F35+G35+$D$10*Inputs!$B$48+Inputs!$B$51+IF(Inputs!$B$13=0,(F35+G35)*(Inputs!$B$12-1),(F35+G35)*(((1+Inputs!$B$13)^Inputs!$B$12-(1+Inputs!$B$13))/Inputs!$B$13)) -> 874320 | I35: =($E$6*Inputs!$B$26*12)+($E$7*Inputs!$B$26*12)+($E$5*Inputs!$B$27*12)+(Inputs!$B$29*12) -> 45000 | J35: =($E$9*1000*12*Inputs!$B$55*Inputs!$B$62)+(Inputs!$B$59*Inputs!$B$62*($E$5/Inputs!$B$6))+(0)+(Inputs!$B$45+Inputs!$B$65)+(Inputs!$B$68*12*Inputs!$B$36) -> 57090 | K35: =I35+J35+$E$10*Inputs!$B$48+Inputs!$B$51+IF(Inputs!$B$13=0,(I35+J35)*(Inputs!$B$12-1),(I35+J35)*(((1+Inputs!$B$13)^Inputs!$B$12-(1+Inputs!$B$13))/Inputs!$B$13)) -> 1360450
A37: Lowest 5-year TCO by scenario
A38: Result | B38: Cloud | C38: S1 Small | F38: S2 Medium | I38: S3 Large
A39: Lowest - Snowflake on AWS (excl. legacy P1) | B39: AWS | C39: =INDEX($A$15:$A$24,MATCH(MIN(E15,E16,E17,E18,E20,E21,E22,E23,E24),E15:E24,0))&" - "&INDEX($B$15:$B$24,MATCH(MIN(E15,E16,E17,E18,E20,E21,E22,E23,E24),E15:E24,0)) -> QuickSight + Snowflake AWS - Standard Author + Reader | E39: =MIN(E15,E16,E17,E18,E20,E21,E22,E23,E24) -> 414200 | F39: =INDEX($A$15:$A$24,MATCH(MIN(H15,H16,H17,H18,H20,H21,H22,H23,H24),H15:H24,0))&" - "&INDEX($B$15:$B$24,MATCH(MIN(H15,H16,H17,H18,H20,H21,H22,H23,H24),H15:H24,0)) -> QuickSight + Snowflake AWS - Standard Author + Reader | H39: =MIN(H15,H16,H17,H18,H20,H21,H22,H23,H24) -> 718800 | I39: =INDEX($A$15:$A$24,MATCH(MIN(K15,K16,K17,K18,K20,K21,K22,K23,K24),K15:K24,0))&" - "&INDEX($B$15:$B$24,MATCH(MIN(K15,K16,K17,K18,K20,K21,K22,K23,K24),K15:K24,0)) -> QuickSight + Snowflake AWS - Standard Author + Reader | K39: =MIN(K15,K16,K17,K18,K20,K21,K22,K23,K24) -> 1137400
A40: Lowest - Snowflake on Azure (excl. legacy P1) | B40: Azure | C40: =INDEX($A$26:$A$35,MATCH(MIN(E26,E27,E28,E29,E31,E32,E33,E34,E35),E26:E35,0))&" - "&INDEX($B$26:$B$35,MATCH(MIN(E26,E27,E28,E29,E31,E32,E33,E34,E35),E26:E35,0)) -> Power BI + Snowflake Azure - Pro - all named | E40: =MIN(E26,E27,E28,E29,E31,E32,E33,E34,E35) -> 434800 | F40: =INDEX($A$26:$A$35,MATCH(MIN(H26,H27,H28,H29,H31,H32,H33,H34,H35),H26:H35,0))&" - "&INDEX($B$26:$B$35,MATCH(MIN(H26,H27,H28,H29,H31,H32,H33,H34,H35),H26:H35,0)) -> Power BI + Snowflake Azure - Pro - all named | H40: =MIN(H26,H27,H28,H29,H31,H32,H33,H34,H35) -> 773400 | I40: =INDEX($A$26:$A$35,MATCH(MIN(K26,K27,K28,K29,K31,K32,K33,K34,K35),K26:K35,0))&" - "&INDEX($B$26:$B$35,MATCH(MIN(K26,K27,K28,K29,K31,K32,K33,K34,K35),K26:K35,0)) -> Power BI + Snowflake Azure - Fabric F64 Reserved + Pro | K40: =MIN(K26,K27,K28,K29,K31,K32,K33,K34,K35) -> 1151160.2
A41: Lowest - all configurations (excl. legacy P1) | B41: All | C41: =INDEX($A$15:$A$35,MATCH(MIN(E15,E16,E17,E18,E20,E21,E22,E23,E24,E26,E27,E28,E29,E31,E32,E33,E34,E35),E15:E35,0))&" - "&INDEX($B$15:$B$35,MATCH(MIN(E15,E16,E17,E18,E20,E21,E22,E23,E24,E26,E27,E28,E29,E31,E32,E33,E34,E35),E15:E35,0)) -> QuickSight + Snowflake AWS - Standard Author + Reader | E41: =MIN(E15,E16,E17,E18,E20,E21,E22,E23,E24,E26,E27,E28,E29,E31,E32,E33,E34,E35) -> 414200 | F41: =INDEX($A$15:$A$35,MATCH(MIN(H15,H16,H17,H18,H20,H21,H22,H23,H24,H26,H27,H28,H29,H31,H32,H33,H34,H35),H15:H35,0))&" - "&INDEX($B$15:$B$35,MATCH(MIN(H15,H16,H17,H18,H20,H21,H22,H23,H24,H26,H27,H28,H29,H31,H32,H33,H34,H35),H15:H35,0)) -> QuickSight + Snowflake AWS - Standard Author + Reader | H41: =MIN(H15,H16,H17,H18,H20,H21,H22,H23,H24,H26,H27,H28,H29,H31,H32,H33,H34,H35) -> 718800 | I41: =INDEX($A$15:$A$35,MATCH(MIN(K15,K16,K17,K18,K20,K21,K22,K23,K24,K26,K27,K28,K29,K31,K32,K33,K34,K35),K15:K35,0))&" - "&INDEX($B$15:$B$35,MATCH(MIN(K15,K16,K17,K18,K20,K21,K22,K23,K24,K26,K27,K28,K29,K31,K32,K33,K34,K35),K15:K35,0)) -> QuickSight + Snowflake AWS - Standard Author + Reader | K41: =MIN(K15,K16,K17,K18,K20,K21,K22,K23,K24,K26,K27,K28,K29,K31,K32,K33,K34,K35) -> 1137400
A43: AI licensing uplift vs standard tier (annual)
A44: Platform | B44: AI tier | C44: S1 Small | F44: S2 Medium | I44: S3 Large
A45: Tableau Cloud | B45: Tableau+ vs Standard | C45: =C21-C20 -> 32160 | F45: =F21-F20 -> 73920 | I45: =I21-I20 -> 140400
A46: QuickSight | B46: Author Pro + Q vs Standard | C46: =C24-C23 -> 6840 | F46: =F24-F23 -> 9720 | I46: =I24-I23 -> 12600
A47: Power BI | B47: Copilot on F64 Reserved | C47: No extra licence - consumes F64 capacity units | F47: No extra licence - consumes F64 capacity units | I47: No extra licence - consumes F64 capacity units

Sheet Cross-Cloud Premium
A1: Cross-Cloud Premium - Power BI with Snowflake on AWS vs Azure, Tableau and QuickSight comparison, and cost-reduction levers
A2: Premium = annual architecture & ops in the cross-cloud placement minus the same-cloud placement. Licensing is identical in both placements, so the premium is the same for every Power BI licensing model.
A3: A. Annual cross-cloud premium by platform (baseline)
A4: Platform | B4: Cross-cloud placement | C4: Transfer | D4: Incremental compute | E4: Gateway / infra | F4: Cross-cloud operations | G4: Annual premium | H4: Interpretation
A5: Power BI | B5: Snowflake on AWS | C5: ='Architecture Costs'!C4-'Architecture Costs'!C5 -> 5400 | D5: ='Architecture Costs'!D4-'Architecture Costs'!D5 -> 12000 | E5: ='Architecture Costs'!E4-'Architecture Costs'!E5 -> 6000 | F5: ='Architecture Costs'!F4-'Architecture Costs'!F5 -> 10000 | G5: ='Architecture Costs'!H4-'Architecture Costs'!H5 -> 33400 | H5: Power BI service runs in Azure; AWS-hosted Snowflake is cross-cloud
A6: Tableau Cloud | B6: Snowflake on Azure | C6: ='Architecture Costs'!C7-'Architecture Costs'!C6 -> 4050 | D6: ='Architecture Costs'!D7-'Architecture Costs'!D6 -> 9000 | E6: ='Architecture Costs'!E7-'Architecture Costs'!E6 -> 0 | F6: ='Architecture Costs'!F7-'Architecture Costs'!F6 -> 8000 | G6: ='Architecture Costs'!H7-'Architecture Costs'!H6 -> 21050 | H6: Tableau Cloud runs on AWS - the premium reverses: it appears when Snowflake is on Azure
A7: Tableau Server | B7: None (self-hosted) | C7: ='Architecture Costs'!C8-'Architecture Costs'!C9 -> 0 | D7: ='Architecture Costs'!D8-'Architecture Costs'!D9 -> 0 | E7: ='Architecture Costs'!E8-'Architecture Costs'!E9 -> 0 | F7: ='Architecture Costs'!F8-'Architecture Costs'!F9 -> 0 | G7: ='Architecture Costs'!H8-'Architecture Costs'!H9 -> 0 | H7: Host Tableau Server beside Snowflake - no premium, but higher infra/ops cost
A8: QuickSight | B8: Snowflake on Azure | C8: ='Architecture Costs'!C11-'Architecture Costs'!C10 -> 6210 | D8: ='Architecture Costs'!D11-'Architecture Costs'!D10 -> 13800 | E8: ='Architecture Costs'!E11-'Architecture Costs'!E10 -> 0 | F8: ='Architecture Costs'!F11-'Architecture Costs'!F10 -> 12000 | G8: ='Architecture Costs'!H11-'Architecture Costs'!H10 -> 32010 | H8: QuickSight is AWS-only; Azure-hosted Snowflake is cross-cloud
A10: B. Power BI cross-cloud premium in context (baseline)
A11: Measure | C11: Value | H11: Note
A12: Annual premium | C12: =G5 -> 33400 | H12: Same for Pro, PPU, Fabric and P1 models
A13: Five-year premium | C13: =G5*Inputs!$B$12 -> 167000 | H13: 0% inflation baseline
A14: Premium as % of 5-year TCO - Fabric F64 Reserved on AWS | C14: =G5*Inputs!$B$12/'TCO Comparison'!I7 -> 0.12669173
A15: Premium as % of 5-year TCO - Pro on AWS | C15: =G5*Inputs!$B$12/'TCO Comparison'!I5 -> 0.11613352
A16: Tableau Cloud premium if Snowflake is on Azure (annual) | C16: =G6 -> 21050 | H16: Not a Snowflake-on-AWS issue for Tableau Cloud
A17: QuickSight premium if Snowflake is on Azure (annual) | C17: =G8 -> 32010
A19: C. Options to reduce the Power BI premium when Snowflake stays on AWS
A20: Lever | B20: Driver input | C20: Annual saving | G20: Residual premium | H20: How / caveat
A21: Baseline premium | B21: - | C21: 0 | G21: =G5 -> 33400 | H21: Transfer + incremental compute + gateway + cross-cloud ops
A22: 1. Import + incremental refresh + aggregations (not DirectQuery) | B22: =TEXT(Inputs!$B$57,"0%")&" traffic cut" -> 80% traffic cut | C22: ='Architecture Costs'!C4*Inputs!$B$57 -> 4320 | G22: =G21-C22 -> 29080 | H22: Move only changed partitions; keep DirectQuery for few freshness-critical visuals
A23: 2. Private path for residual traffic (Direct Connect / interconnect) | B23: =TEXT(Inputs!$B$56,"$0.00")&" per GB" -> $0.02 per GB | C23: ='Architecture Costs'!C4*(1-Inputs!$B$57)*(1-Inputs!$B$56/Inputs!$B$55) -> 840 | G23: =G22-C23 -> 28240 | H23: Variable rate only; circuit/port fees excluded - worthwhile mainly at higher volumes
A24: 3. Snowflake workload tuning (result cache, aggregates, auto-suspend, right-sized BI warehouse) | B24: =TEXT(Inputs!$B$58,"0%")&" compute cut" -> 50% compute cut | C24: ='Architecture Costs'!D4*Inputs!$B$58 -> 6000 | G24: =G23-C24 -> 22240 | H24: Dedicated XS/S BI warehouse with 60s auto-suspend; materialised aggregates
A25: Optimised annual premium (levers 1-3) | C25: =SUM(C21:C24) -> 11160 | G25: =G24 -> 22240 | H25: Residual = gateway + cross-cloud operations + remaining transfer/compute
A26: Optimised five-year premium | C26: =G25*Inputs!$B$12 -> 111200 | H26: vs unoptimised five-year premium in section B
A28: D. Further options (not modelled numerically)
A29: Option | C29: Effect on premium | H29: Trade-off
A30: Fabric F64 Reserved instead of Pro for all | C30: Licensing saving (not cross-cloud) | H30: Saves the licence difference shown in TCO Comparison; Copilot available; capacity must be sized
A31: Fabric Mirroring of curated Snowflake tables into OneLake | C31: Removes repeat dashboard queries | H31: Second governed copy; Fabric query capacity; RLS/CLS recreated; reseed risk
A32: Snowflake replica in Azure for BI-serving data only | C32: Same-cloud BI reads | H32: Replication egress + second account compute/storage; adds operational ownership
A33: Standardise on a same-cloud BI tool | C33: Eliminates premium | H33: QuickSight (AWS) or Tableau Cloud (AWS); trade-off vs Power BI semantic and M365 strengths
A35: Note: Snowflake does not charge data egress when a client/driver retrieves query results across clouds; the $/GB line represents AWS-side network egress (EC2 gateway/NAT) and is a conservative sensitivity - confirm with an AWS billing test in the PoV.

Sheet Sources
A1: Pricing Sources and Validation - checked 23 October 2026
A3: Vendor / topic | B3: Input used | C3: Public source URL | D3: Status | E3: Important caveat
A4: Microsoft Power BI | B4: $14 Pro; $24 PPU (per user/month, paid yearly) | C4: https://www.microsoft.com/en-us/power-platform/products/power-bi/pricing | D4: Verified | E4: Country/contract pricing may differ; Pro required to publish to any P or F capacity
A5: Fabric capacity | B5: F64 PAYG $8,409.60/month; 1-yr reserved $5,002.67/month | C5: https://azure.microsoft.com/en-us/pricing/details/microsoft-fabric/ | D5: Verified (US) | E5: Official page quotes ~41% reservation saving; region pricing varies
A6: Power BI capacity viewing | B6: Free viewers only at F64+ / P1+ | C6: https://learn.microsoft.com/en-us/power-bi/fundamentals/service-features-license-type | D6: Verified | E6: Authors still require Pro
A7: Premium P1 (legacy) | B7: $4,995/month reference | C7: https://learn.microsoft.com/en-us/power-bi/support/premium-migration-overview | D7: Verified | E7: Microsoft no longer sells new P SKUs; renewals only under active EA
A8: Power BI Copilot | B8: Requires paid Fabric F2+ or P1+ (or Fabric Copilot capacity) | C8: https://learn.microsoft.com/en-us/power-bi/create-reports/copilot-enable-power-bi | D8: Verified | E8: Not available on trial capacities; consumes capacity units
A9: Tableau Standard | B9: $75 Creator; $42 Explorer; $15 Viewer | C9: https://www.tableau.com/pricing/cloud ; https://www.tableau.com/pricing/server | D9: Verified | E9: Same list for Cloud and Server; annual contract
A10: Tableau Enterprise / Tableau+ | B10: Enterprise $115 / $70 / $35 used as Tableau+ floor | C10: https://www.tableau.com/pricing/cloud | D10: Quote-only | E10: Tableau+ price not published - obtain Salesforce quote
A11: Tableau Cloud hosting | B11: Runs on Salesforce Hyperforce on AWS | C11: https://aws.amazon.com/blogs/migration-and-modernization/migration-of-tableau-cloud-to-salesforce-hyperforce-on-aws/ | D11: Verified | E11: Choose site region matching Snowflake region
A12: Amazon QuickSight | B12: $24 Author; $40 Author Pro; $3 Reader; $20 Reader Pro; $250/account/month Pro fee | C12: https://aws.amazon.com/quick/quicksight/pricing/ | D12: Verified | E12: Now 'Amazon Quick Sight' within Amazon Quick Suite; Author includes NL Q&A
A13: Snowflake compute | B13: $3.00/credit Enterprise (AWS US East on-demand) | C13: https://www.snowflake.com/pricing/pricing-guide | D13: Verified | E13: Business Critical $4.00 - use if IDB requires it
A14: Snowflake data transfer | B14: $0.09/GB ($90/TB) to other cloud or internet | C14: https://www.snowflake.com/pricing/pricing-guide | D14: Verified | E14: Snowflake does not bill egress for driver-retrieved query results
... A18: Model status | B18: Illustrative; not a vendor quote | C18: User inputs + public sources | D18: - | E18: Replace yellow cells with IDB quotes and PoV measurements

Sheet Change Log
A1: Change Log - v2 (23 October 2026)
A3: # | B3: Change | C3: Detail / impact
A4: 1 | B4: Snowflake credit rate populated | C4: Inputs credit rate was blank, so base Snowflake compute was $0 in every config. Set to $3.00 (Enterprise, AWS US East) - adds $10,800/yr (300 credits) or $10,080/yr (QuickSight, 280 credits).
A5: 2 | B5: All 20 configurations modelled on every sheet | C5: Added Premium P1 + Pro and Tableau+ (AI tier). TCO Comparison, Scenario Simulator and Dashboard now carry all 20 rows; Scenario Simulator previously covered 6.
A6: 3 | B6: Fabric F64 rates aligned to list | C6: Monthly inputs $8,409.60 PAYG / $5,002.67 reserved (previously rounded annuals $100,908 / $60,000).
A7: 4 | B7: Tableau+ priced from Enterprise list floor | C7: Tableau+ is quote-only. Previous POV used $115/$70/$25 - the $25 viewer is below the $35 Enterprise list, so Tableau+ was understated. Now $115/$70/$35.
A8: 5 | B8: QuickSight explorers licensed | C8: 25 explorers/analysts were unlicensed in QuickSight rows (free) while licensed on Power BI and Tableau. Now licensed as Authors (Standard) or Author Pro (AI tier).
A9: 6 | B9: Tableau Cloud placement corrected | C9: Tableau Cloud runs on Salesforce Hyperforce on AWS. With Snowflake on AWS it is same-cloud (factor 0); with Snowflake on Azure it is cross-cloud (factor 0.75). Previously both placements carried the same cross-cloud cost.
A10: 7 | B10: Cross-Cloud Premium sheet added | C10: Answers: Power BI premium with Snowflake on AWS vs Azure, whether Tableau has the same issue, and cost-reduction levers (uses previously unused private-path and import-reduction inputs).
A11: 8 | B11: Break-even checks added | C11: F64 vs Pro, PAYG vs Pro and PPU vs F64 break-evens computed from inputs.
A12: 9 | B12: AI uplift computed by scenario | C12: Tableau+ and QuickSight Pro uplifts derived from Scenario Simulator rows.
A13: 10 | B13: Sources re-validated | C13: Every list price checked against vendor pages on 23 Oct 2026; status column added.
A14: 11 | B14: Consistent formatting | C14: Arial throughout, one header style, yellow/blue input convention, frozen panes.
